[
    {
        "name": "Hedwigs Theme Harry Potter",
        "type": "recorded",
        "folderId": null,
        "instruments": [
            {
                "name": "Piano",
                "volume": 100,
                "pitch": "",
                "visible": true,
                "icon": "circle",
                "alias": "",
                "muted": false,
                "reverbOverride": null
            }
        ],
        "version": 2,
        "pitch": "C",
        "bpm": 220,
        "reverb": false,
        "data": {
            "isComposed": false,
            "isComposedVersion": false,
            "appName": "Sky"
        },
        "notes": [
            [
                5,
                818,
                "1"
            ],
            [
                1,
                1266,
                "1"
            ],
            [
                8,
                1291,
                "1"
            ],
            [
                10,
                1932,
                "1"
            ],
            [
                9,
                2159,
                "1"
            ],
            [
                1,
                2560,
                "1"
            ],
            [
                8,
                2563,
                "1"
            ],
            [
                12,
                3406,
                "1"
            ],
            [
                1,
                3842,
                "1"
            ],
            [
                11,
                3855,
                "1"
            ],
            [
                1,
                5188,
                "1"
            ],
            [
                9,
                5200,
                "1"
            ],
            [
                8,
                6466,
                "1"
            ],
            [
                3,
                6472,
                "1"
            ],
            [
                10,
                7134,
                "1"
            ],
            [
                9,
                7341,
                "1"
            ],
            [
                2,
                7770,
                "1"
            ],
            [
                7,
                7776,
                "1"
            ],
            [
                0,
                8600,
                "1"
            ],
            [
                9,
                8622,
                "1"
            ],
            [
                5,
                9061,
                "1"
            ],
            [
                1,
                9067,
                "1"
            ],
            [
                3,
                9983,
                "1"
            ],
            [
                5,
                10434,
                "1"
            ],
            [
                5,
                11312,
                "1"
            ],
            [
                1,
                11753,
                "1"
            ],
            [
                8,
                11795,
                "1"
            ],
            [
                10,
                12464,
                "1"
            ],
            [
                9,
                12628,
                "1"
            ],
            [
                1,
                13033,
                "1"
            ],
            [
                8,
                13057,
                "1"
            ],
            [
                12,
                13897,
                "1"
            ],
            [
                0,
                14305,
                "1"
            ],
            [
                7,
                14337,
                "1"
            ],
            [
                3,
                14349,
                "1"
            ],
            [
                14,
                14379,
                "1"
            ],
            [
                13,
                15249,
                "1"
            ],
            [
                5,
                15675,
                "1"
            ],
            [
                12,
                15691,
                "1"
            ],
            [
                8,
                15698,
                "1"
            ],
            [
                3,
                15721,
                "1"
            ],
            [
                11,
                16647,
                "1"
            ],
            [
                1,
                17069,
                "1"
            ],
            [
                12,
                17085,
                "1"
            ],
            [
                8,
                17120,
                "1"
            ],
            [
                3,
                17123,
                "1"
            ],
            [
                10,
                17822,
                "1"
            ],
            [
                8,
                18036,
                "1"
            ],
            [
                5,
                18467,
                "1"
            ],
            [
                1,
                18478,
                "1"
            ],
            [
                3,
                18514,
                "1"
            ],
            [
                10,
                19380,
                "1"
            ],
            [
                8,
                19851,
                "1"
            ],
            [
                1,
                19863,
                "1"
            ],
            [
                3,
                20770,
                "1"
            ],
            [
                5,
                21206,
                "1"
            ],
            [
                0,
                22069,
                "1"
            ],
            [
                1,
                22524,
                "1"
            ],
            [
                3,
                23419,
                "1"
            ],
            [
                5,
                23898,
                "1"
            ],
            [
                0,
                24770,
                "1"
            ],
            [
                10,
                24809,
                "1"
            ],
            [
                12,
                25196,
                "1"
            ],
            [
                1,
                25215,
                "1"
            ],
            [
                10,
                26049,
                "1"
            ],
            [
                3,
                26068,
                "1"
            ],
            [
                5,
                26531,
                "1"
            ],
            [
                12,
                26533,
                "1"
            ],
            [
                10,
                27407,
                "1"
            ],
            [
                0,
                27412,
                "1"
            ],
            [
                1,
                27866,
                "1"
            ],
            [
                12,
                27871,
                "1"
            ],
            [
                11,
                28729,
                "1"
            ],
            [
                3,
                28773,
                "1"
            ],
            [
                4,
                29171,
                "1"
            ],
            [
                9,
                29175,
                "1"
            ],
            [
                8,
                30502,
                "1"
            ],
            [
                3,
                30509,
                "1"
            ],
            [
                10,
                31116,
                "1"
            ],
            [
                9,
                31319,
                "1"
            ],
            [
                2,
                31766,
                "1"
            ],
            [
                7,
                31773,
                "1"
            ],
            [
                8,
                32573,
                "1"
            ],
            [
                0,
                32610,
                "1"
            ],
            [
                1,
                33047,
                "1"
            ],
            [
                12,
                33062,
                "1"
            ],
            [
                3,
                33905,
                "1"
            ],
            [
                5,
                34364,
                "1"
            ],
            [
                10,
                35200,
                "1"
            ],
            [
                0,
                35216,
                "1"
            ],
            [
                12,
                35654,
                "1"
            ],
            [
                1,
                35669,
                "1"
            ],
            [
                10,
                36556,
                "1"
            ],
            [
                3,
                36564,
                "1"
            ],
            [
                5,
                37005,
                "1"
            ],
            [
                12,
                37044,
                "1"
            ],
            [
                10,
                37850,
                "1"
            ],
            [
                0,
                38277,
                "1"
            ],
            [
                5,
                38299,
                "1"
            ],
            [
                3,
                38332,
                "1"
            ],
            [
                14,
                38335,
                "1"
            ],
            [
                13,
                39147,
                "1"
            ],
            [
                5,
                39623,
                "1"
            ],
            [
                2,
                39629,
                "1"
            ],
            [
                12,
                39638,
                "1"
            ],
            [
                11,
                40488,
                "1"
            ],
            [
                12,
                40947,
                "1"
            ],
            [
                8,
                40961,
                "1"
            ],
            [
                1,
                40978,
                "1"
            ],
            [
                3,
                40980,
                "1"
            ],
            [
                10,
                41824,
                "1"
            ],
            [
                8,
                41972,
                "1"
            ],
            [
                5,
                42389,
                "1"
            ],
            [
                1,
                42396,
                "1"
            ],
            [
                3,
                42401,
                "1"
            ],
            [
                10,
                43357,
                "1"
            ],
            [
                8,
                43833,
                "1"
            ],
            [
                1,
                43848,
                "1"
            ],
            [
                3,
                44746,
                "1"
            ],
            [
                5,
                45230,
                "1"
            ],
            [
                0,
                46034,
                "1"
            ],
            [
                1,
                46495,
                "1"
            ],
            [
                3,
                47398,
                "1"
            ],
            [
                5,
                47859,
                "1"
            ],
            [
                0,
                48763,
                "1"
            ],
            [
                1,
                49392,
                "1"
            ]
        ],
        "id": "f7db37bd-930d-3f39-08f7",
        "isComposed": false,
        "pitchLevel": 0,
        "bitsPerPage": 16,
        "isEncrypted": false,
        "songNotes": [
            {
                "time": 818,
                "key": "1Key5"
            },
            {
                "time": 1266,
                "key": "1Key1"
            },
            {
                "time": 1291,
                "key": "1Key8"
            },
            {
                "time": 1932,
                "key": "1Key10"
            },
            {
                "time": 2159,
                "key": "1Key9"
            },
            {
                "time": 2560,
                "key": "1Key1"
            },
            {
                "time": 2563,
                "key": "1Key8"
            },
            {
                "time": 3406,
                "key": "1Key12"
            },
            {
                "time": 3842,
                "key": "1Key1"
            },
            {
                "time": 3855,
                "key": "1Key11"
            },
            {
                "time": 5188,
                "key": "1Key1"
            },
            {
                "time": 5200,
                "key": "1Key9"
            },
            {
                "time": 6466,
                "key": "1Key8"
            },
            {
                "time": 6472,
                "key": "1Key3"
            },
            {
                "time": 7134,
                "key": "1Key10"
            },
            {
                "time": 7341,
                "key": "1Key9"
            },
            {
                "time": 7770,
                "key": "1Key2"
            },
            {
                "time": 7776,
                "key": "1Key7"
            },
            {
                "time": 8600,
                "key": "1Key0"
            },
            {
                "time": 8622,
                "key": "1Key9"
            },
            {
                "time": 9061,
                "key": "1Key5"
            },
            {
                "time": 9067,
                "key": "1Key1"
            },
            {
                "time": 9983,
                "key": "1Key3"
            },
            {
                "time": 10434,
                "key": "1Key5"
            },
            {
                "time": 11312,
                "key": "1Key5"
            },
            {
                "time": 11753,
                "key": "1Key1"
            },
            {
                "time": 11795,
                "key": "1Key8"
            },
            {
                "time": 12464,
                "key": "1Key10"
            },
            {
                "time": 12628,
                "key": "1Key9"
            },
            {
                "time": 13033,
                "key": "1Key1"
            },
            {
                "time": 13057,
                "key": "1Key8"
            },
            {
                "time": 13897,
                "key": "1Key12"
            },
            {
                "time": 14305,
                "key": "1Key0"
            },
            {
                "time": 14337,
                "key": "1Key7"
            },
            {
                "time": 14349,
                "key": "1Key3"
            },
            {
                "time": 14379,
                "key": "1Key14"
            },
            {
                "time": 15249,
                "key": "1Key13"
            },
            {
                "time": 15675,
                "key": "1Key5"
            },
            {
                "time": 15691,
                "key": "1Key12"
            },
            {
                "time": 15698,
                "key": "1Key8"
            },
            {
                "time": 15721,
                "key": "1Key3"
            },
            {
                "time": 16647,
                "key": "1Key11"
            },
            {
                "time": 17069,
                "key": "1Key1"
            },
            {
                "time": 17085,
                "key": "1Key12"
            },
            {
                "time": 17120,
                "key": "1Key8"
            },
            {
                "time": 17123,
                "key": "1Key3"
            },
            {
                "time": 17822,
                "key": "1Key10"
            },
            {
                "time": 18036,
                "key": "1Key8"
            },
            {
                "time": 18467,
                "key": "1Key5"
            },
            {
                "time": 18478,
                "key": "1Key1"
            },
            {
                "time": 18514,
                "key": "1Key3"
            },
            {
                "time": 19380,
                "key": "1Key10"
            },
            {
                "time": 19851,
                "key": "1Key8"
            },
            {
                "time": 19863,
                "key": "1Key1"
            },
            {
                "time": 20770,
                "key": "1Key3"
            },
            {
                "time": 21206,
                "key": "1Key5"
            },
            {
                "time": 22069,
                "key": "1Key0"
            },
            {
                "time": 22524,
                "key": "1Key1"
            },
            {
                "time": 23419,
                "key": "1Key3"
            },
            {
                "time": 23898,
                "key": "1Key5"
            },
            {
                "time": 24770,
                "key": "1Key0"
            },
            {
                "time": 24809,
                "key": "1Key10"
            },
            {
                "time": 25196,
                "key": "1Key12"
            },
            {
                "time": 25215,
                "key": "1Key1"
            },
            {
                "time": 26049,
                "key": "1Key10"
            },
            {
                "time": 26068,
                "key": "1Key3"
            },
            {
                "time": 26531,
                "key": "1Key5"
            },
            {
                "time": 26533,
                "key": "1Key12"
            },
            {
                "time": 27407,
                "key": "1Key10"
            },
            {
                "time": 27412,
                "key": "1Key0"
            },
            {
                "time": 27866,
                "key": "1Key1"
            },
            {
                "time": 27871,
                "key": "1Key12"
            },
            {
                "time": 28729,
                "key": "1Key11"
            },
            {
                "time": 28773,
                "key": "1Key3"
            },
            {
                "time": 29171,
                "key": "1Key4"
            },
            {
                "time": 29175,
                "key": "1Key9"
            },
            {
                "time": 30502,
                "key": "1Key8"
            },
            {
                "time": 30509,
                "key": "1Key3"
            },
            {
                "time": 31116,
                "key": "1Key10"
            },
            {
                "time": 31319,
                "key": "1Key9"
            },
            {
                "time": 31766,
                "key": "1Key2"
            },
            {
                "time": 31773,
                "key": "1Key7"
            },
            {
                "time": 32573,
                "key": "1Key8"
            },
            {
                "time": 32610,
                "key": "1Key0"
            },
            {
                "time": 33047,
                "key": "1Key1"
            },
            {
                "time": 33062,
                "key": "1Key12"
            },
            {
                "time": 33905,
                "key": "1Key3"
            },
            {
                "time": 34364,
                "key": "1Key5"
            },
            {
                "time": 35200,
                "key": "1Key10"
            },
            {
                "time": 35216,
                "key": "1Key0"
            },
            {
                "time": 35654,
                "key": "1Key12"
            },
            {
                "time": 35669,
                "key": "1Key1"
            },
            {
                "time": 36556,
                "key": "1Key10"
            },
            {
                "time": 36564,
                "key": "1Key3"
            },
            {
                "time": 37005,
                "key": "1Key5"
            },
            {
                "time": 37044,
                "key": "1Key12"
            },
            {
                "time": 37850,
                "key": "1Key10"
            },
            {
                "time": 38277,
                "key": "1Key0"
            },
            {
                "time": 38299,
                "key": "1Key5"
            },
            {
                "time": 38332,
                "key": "1Key3"
            },
            {
                "time": 38335,
                "key": "1Key14"
            },
            {
                "time": 39147,
                "key": "1Key13"
            },
            {
                "time": 39623,
                "key": "1Key5"
            },
            {
                "time": 39629,
                "key": "1Key2"
            },
            {
                "time": 39638,
                "key": "1Key12"
            },
            {
                "time": 40488,
                "key": "1Key11"
            },
            {
                "time": 40947,
                "key": "1Key12"
            },
            {
                "time": 40961,
                "key": "1Key8"
            },
            {
                "time": 40978,
                "key": "1Key1"
            },
            {
                "time": 40980,
                "key": "1Key3"
            },
            {
                "time": 41824,
                "key": "1Key10"
            },
            {
                "time": 41972,
                "key": "1Key8"
            },
            {
                "time": 42389,
                "key": "1Key5"
            },
            {
                "time": 42396,
                "key": "1Key1"
            },
            {
                "time": 42401,
                "key": "1Key3"
            },
            {
                "time": 43357,
                "key": "1Key10"
            },
            {
                "time": 43833,
                "key": "1Key8"
            },
            {
                "time": 43848,
                "key": "1Key1"
            },
            {
                "time": 44746,
                "key": "1Key3"
            },
            {
                "time": 45230,
                "key": "1Key5"
            },
            {
                "time": 46034,
                "key": "1Key0"
            },
            {
                "time": 46495,
                "key": "1Key1"
            },
            {
                "time": 47398,
                "key": "1Key3"
            },
            {
                "time": 47859,
                "key": "1Key5"
            },
            {
                "time": 48763,
                "key": "1Key0"
            },
            {
                "time": 49392,
                "key": "1Key1"
            }
        ]
    }
]