[{"name":"Cat Vibin / Levan Polkka (Medium-Hard)  (SaiCode)","type":"composed","bpm":480,"pitch":"C","version":3,"folderId":null,"data":{"isComposed":true,"isComposedVersion":true,"appName":"Sky"},"reverb":false,"breakpoints":[0],"instruments":[{"name":"Piano","volume":100,"pitch":"","visible":true,"icon":"circle","alias":"","muted":false,"reverbOverride":null}],"columns":[[0,[[5,"1"]]],[0,[]],[0,[[7,"1"],[9,"1"]]],[0,[]],[0,[[2,"1"]]],[0,[]],[0,[[7,"1"],[9,"1"]]],[0,[]],[0,[[5,"1"]]],[0,[]],[0,[[7,"1"],[9,"1"]]],[0,[]],[0,[[2,"1"]]],[0,[]],[0,[[4,"1"],[7,"1"],[9,"1"]]],[0,[]],[0,[[5,"1"]]],[0,[]],[0,[[7,"1"],[9,"1"]]],[0,[]],[0,[[2,"1"]]],[0,[]],[0,[[7,"1"],[9,"1"]]],[0,[]],[0,[[5,"1"]]],[0,[]],[0,[[7,"1"],[9,"1"]]],[0,[]],[0,[[2,"1"]]],[0,[]],[0,[[4,"1"],[7,"1"],[9,"1"]]],[0,[]],[0,[[5,"1"]]],[0,[]],[0,[[7,"1"],[9,"1"]]],[0,[]],[0,[[2,"1"]]],[0,[]],[0,[[7,"1"],[9,"1"]]],[0,[]],[0,[[5,"1"]]],[0,[]],[0,[[7,"1"],[9,"1"]]],[0,[]],[0,[[2,"1"]]],[0,[]],[0,[[4,"1"],[7,"1"],[9,"1"]]],[0,[]],[0,[[5,"1"]]],[0,[]],[0,[[7,"1"],[9,"1"]]],[0,[]],[0,[[2,"1"]]],[0,[]],[0,[[7,"1"],[9,"1"]]],[0,[]],[0,[[5,"1"]]],[0,[]],[0,[[7,"1"],[9,"1"]]],[0,[]],[0,[[2,"1"]]],[0,[]],[0,[[4,"1"],[7,"1"],[9,"1"]]],[0,[]],[0,[[5,"1"]]],[0,[]],[0,[[7,"1"],[9,"1"]]],[0,[]],[0,[[2,"1"]]],[0,[]],[0,[[7,"1"],[9,"1"]]],[0,[]],[0,[[5,"1"]]],[0,[]],[0,[[7,"1"],[9,"1"]]],[0,[]],[0,[[2,"1"]]],[0,[]],[0,[[4,"1"],[7,"1"],[9,"1"]]],[0,[]],[0,[[5,"1"]]],[0,[]],[0,[[7,"1"],[9,"1"]]],[0,[]],[0,[[2,"1"]]],[0,[]],[0,[[7,"1"],[9,"1"]]],[0,[]],[0,[[5,"1"]]],[0,[]],[0,[[7,"1"],[9,"1"]]],[0,[]],[0,[[2,"1"]]],[0,[]],[0,[[4,"1"],[7,"1"],[9,"1"]]],[0,[]],[0,[[5,"1"]]],[0,[]],[0,[[7,"1"],[9,"1"]]],[0,[]],[0,[[2,"1"]]],[0,[]],[0,[[7,"1"],[9,"1"]]],[0,[]],[0,[[5,"1"]]],[0,[]],[0,[[7,"1"],[9,"1"]]],[0,[]],[0,[[2,"1"]]],[0,[]],[0,[[4,"1"],[7,"1"],[9,"1"]]],[0,[]],[0,[[5,"1"]]],[0,[]],[0,[[7,"1"],[9,"1"]]],[0,[]],[0,[[2,"1"]]],[0,[]],[0,[[7,"1"],[9,"1"]]],[0,[]],[0,[[5,"1"],[7,"1"],[9,"1"]]],[0,[]],[0,[]],[0,[]],[1,[]],[0,[[5,"1"]]],[0,[[2,"1"],[5,"1"]]],[0,[]],[0,[[5,"1"],[7,"1"],[9,"1"]]],[0,[]],[0,[[2,"1"],[5,"1"]]],[0,[]],[0,[[4,"1"],[7,"1"],[9,"1"]]],[0,[[6,"1"]]],[0,[[5,"1"],[7,"1"]]],[0,[[7,"1"]]],[0,[[5,"1"],[7,"1"],[9,"1"]]],[0,[[5,"1"]]],[0,[[2,"1"],[5,"1"]]],[0,[]],[0,[[4,"1"],[5,"1"],[7,"1"],[9,"1"]]],[0,[[7,"1"]]],[0,[[2,"1"],[6,"1"]]],[0,[]],[0,[[4,"1"],[6,"1"],[9,"1"]]],[0,[]],[0,[[4,"1"]]],[0,[]],[0,[[2,"1"],[4,"1"],[6,"1"],[9,"1"]]],[0,[]],[0,[[5,"1"],[6,"1"]]],[0,[]],[0,[[5,"1"],[7,"1"],[9,"1"]]],[0,[]],[0,[[2,"1"],[5,"1"]]],[0,[]],[0,[[4,"1"],[5,"1"],[7,"1"],[9,"1"]]],[0,[[5,"1"]]],[0,[[2,"1"],[5,"1"]]],[0,[]],[0,[[5,"1"],[7,"1"],[9,"1"]]],[0,[]],[0,[[2,"1"],[5,"1"]]],[0,[]],[0,[[4,"1"],[7,"1"],[9,"1"]]],[0,[[6,"1"]]],[0,[[5,"1"],[7,"1"]]],[0,[]],[0,[[5,"1"],[7,"1"],[9,"1"]]],[0,[[5,"1"]]],[0,[[2,"1"]]],[0,[[5,"1"]]],[0,[[4,"1"],[5,"1"],[7,"1"],[9,"1"]]],[0,[[7,"1"]]],[0,[[2,"1"],[9,"1"]]],[0,[[9,"1"]]],[0,[[6,"1"],[9,"1"]]],[0,[[8,"1"]]],[0,[[4,"1"],[7,"1"]]],[0,[[7,"1"]]],[0,[[2,"1"],[6,"1"],[9,"1"]]],[0,[]],[0,[[5,"1"],[7,"1"]]],[0,[]],[0,[[5,"1"],[7,"1"],[9,"1"]]],[0,[]],[0,[[2,"1"],[5,"1"]]],[0,[]],[0,[[4,"1"],[5,"1"],[7,"1"],[9,"1"]]],[0,[[5,"1"]]],[0,[[5,"1"],[9,"1"]]],[0,[]],[0,[[7,"1"],[9,"1"]]],[0,[]],[0,[[2,"1"],[8,"1"]]],[0,[]],[0,[[4,"1"],[7,"1"],[9,"1"]]],[0,[]],[0,[[2,"1"],[6,"1"]]],[0,[]],[0,[[4,"1"],[7,"1"],[9,"1"]]],[0,[[4,"1"]]],[0,[[2,"1"]]],[0,[[4,"1"]]],[0,[[4,"1"],[7,"1"],[9,"1"]]],[0,[[6,"1"]]],[0,[[2,"1"],[8,"1"]]],[0,[[8,"1"]]],[0,[[6,"1"],[8,"1"],[9,"1"]]],[0,[[8,"1"]]],[0,[[4,"1"],[7,"1"]]],[0,[[7,"1"]]],[0,[[2,"1"],[6,"1"],[9,"1"]]],[0,[[6,"1"]]],[0,[[5,"1"],[7,"1"]]],[0,[]],[0,[[5,"1"],[7,"1"],[9,"1"]]],[0,[[5,"1"]]],[0,[[2,"1"]]],[0,[]],[0,[[4,"1"],[7,"1"],[9,"1"]]],[0,[[5,"1"]]],[0,[[5,"1"],[9,"1"]]],[0,[]],[0,[[7,"1"],[9,"1"]]],[0,[]],[0,[[2,"1"],[8,"1"]]],[0,[]],[0,[[4,"1"],[7,"1"],[9,"1"]]],[0,[]],[0,[[2,"1"],[6,"1"]]],[0,[]],[0,[[4,"1"],[7,"1"],[9,"1"]]],[0,[]],[0,[[2,"1"],[4,"1"]]],[0,[]],[0,[[4,"1"],[7,"1"],[9,"1"]]],[0,[[6,"1"]]],[0,[[2,"1"],[8,"1"]]],[0,[[8,"1"]]],[0,[[6,"1"],[8,"1"],[9,"1"]]],[0,[[8,"1"]]],[0,[[4,"1"],[7,"1"]]],[0,[]],[0,[[2,"1"],[6,"1"],[9,"1"]]],[0,[]],[0,[[5,"1"],[7,"1"],[9,"1"]]],[0,[]],[0,[[5,"1"]]],[0,[[5,"1"]]],[0,[]],[0,[]],[0,[[5,"1"]]],[0,[[2,"1"],[5,"1"]]],[0,[]],[0,[[5,"1"],[7,"1"],[9,"1"]]],[0,[]],[0,[[2,"1"],[5,"1"]]],[0,[]],[0,[[4,"1"],[7,"1"],[9,"1"]]],[0,[[6,"1"]]],[0,[[5,"1"],[7,"1"]]],[0,[[7,"1"]]],[0,[[5,"1"],[7,"1"],[9,"1"]]],[0,[[5,"1"]]],[0,[[2,"1"],[5,"1"]]],[0,[]],[0,[[4,"1"],[5,"1"],[7,"1"],[9,"1"]]],[0,[[7,"1"]]],[0,[[2,"1"],[6,"1"]]],[0,[]],[0,[[4,"1"],[6,"1"],[9,"1"]]],[0,[]],[0,[[4,"1"]]],[0,[]],[0,[[2,"1"],[4,"1"],[6,"1"],[9,"1"]]],[0,[]],[0,[[5,"1"],[6,"1"]]],[0,[]],[0,[[5,"1"],[7,"1"],[9,"1"]]],[0,[]],[0,[[2,"1"],[5,"1"]]],[0,[]],[0,[[4,"1"],[5,"1"],[7,"1"],[9,"1"]]],[0,[[5,"1"]]],[0,[[2,"1"],[5,"1"]]],[0,[]],[0,[[5,"1"],[7,"1"],[9,"1"]]],[0,[]],[0,[[2,"1"],[5,"1"]]],[0,[]],[0,[[4,"1"],[7,"1"],[9,"1"]]],[0,[[6,"1"]]],[0,[[5,"1"],[7,"1"]]],[0,[]],[0,[[5,"1"],[7,"1"],[9,"1"]]],[0,[[5,"1"]]],[0,[[2,"1"]]],[0,[[5,"1"]]],[0,[[4,"1"],[5,"1"],[7,"1"],[9,"1"]]],[0,[[7,"1"]]],[0,[[2,"1"],[9,"1"]]],[0,[[9,"1"]]],[0,[[6,"1"],[9,"1"]]],[0,[[8,"1"]]],[0,[[4,"1"],[7,"1"]]],[0,[[7,"1"]]],[0,[[2,"1"],[6,"1"],[9,"1"]]],[0,[]],[0,[[5,"1"],[7,"1"]]],[0,[]],[0,[[5,"1"],[7,"1"],[9,"1"]]],[0,[]],[0,[[2,"1"],[5,"1"]]],[0,[]],[0,[[4,"1"],[5,"1"],[7,"1"],[9,"1"]]],[0,[[5,"1"]]],[0,[[5,"1"],[9,"1"]]],[0,[]],[0,[[7,"1"],[9,"1"]]],[0,[]],[0,[[2,"1"],[8,"1"]]],[0,[]],[0,[[4,"1"],[7,"1"],[9,"1"]]],[0,[]],[0,[[2,"1"],[6,"1"]]],[0,[]],[0,[[4,"1"],[7,"1"],[9,"1"]]],[0,[[4,"1"]]],[0,[[2,"1"]]],[0,[[4,"1"]]],[0,[[4,"1"],[7,"1"],[9,"1"]]],[0,[[6,"1"]]],[0,[[2,"1"],[8,"1"]]],[0,[[8,"1"]]],[0,[[6,"1"],[8,"1"],[9,"1"]]],[0,[[8,"1"]]],[0,[[4,"1"],[7,"1"]]],[0,[[7,"1"]]],[0,[[2,"1"],[6,"1"],[9,"1"]]],[0,[[6,"1"]]],[0,[[5,"1"],[7,"1"]]],[0,[]],[0,[[5,"1"],[7,"1"],[9,"1"]]],[0,[[5,"1"]]],[0,[[2,"1"]]],[0,[]],[0,[[4,"1"],[7,"1"],[9,"1"]]],[0,[[5,"1"]]],[0,[[5,"1"],[9,"1"]]],[0,[]],[0,[[7,"1"],[9,"1"]]],[0,[]],[0,[[2,"1"],[8,"1"]]],[0,[]],[0,[[4,"1"],[7,"1"],[9,"1"]]],[0,[]],[0,[[2,"1"],[6,"1"]]],[0,[]],[0,[[4,"1"],[7,"1"],[9,"1"]]],[0,[]],[0,[[2,"1"],[4,"1"]]],[0,[]],[0,[[4,"1"],[7,"1"],[9,"1"]]],[0,[[6,"1"]]],[0,[[2,"1"],[8,"1"]]],[0,[[8,"1"]]],[0,[[6,"1"],[8,"1"],[9,"1"]]],[0,[[8,"1"]]],[0,[[4,"1"],[7,"1"]]],[0,[]],[0,[[2,"1"],[6,"1"],[9,"1"]]],[0,[]],[0,[[5,"1"],[7,"1"],[9,"1"]]],[0,[]],[0,[[5,"1"]]],[0,[[5,"1"]]],[0,[]],[0,[]],[1,[]],[0,[[5,"1"]]],[0,[]],[0,[]],[0,[[2,"1"]]],[0,[]],[0,[[4,"1"]]],[0,[]],[0,[[5,"1"]]],[0,[]],[0,[]],[0,[[2,"1"]]],[0,[]],[0,[[4,"1"]]],[0,[]],[0,[[2,"1"]]],[0,[]],[0,[]],[0,[[4,"1"]]],[0,[]],[0,[[2,"1"]]],[0,[]],[0,[[5,"1"]]],[0,[]],[0,[]],[0,[[2,"1"]]],[0,[]],[0,[[4,"1"]]],[0,[]],[0,[[5,"1"]]],[0,[]],[0,[]],[0,[[2,"1"]]],[0,[]],[0,[[4,"1"]]],[0,[]],[0,[[5,"1"]]],[0,[]],[0,[]],[0,[[2,"1"]]],[0,[]],[0,[[4,"1"]]],[0,[]],[0,[[2,"1"]]],[0,[]],[0,[]],[0,[[4,"1"]]],[0,[]],[0,[[2,"1"]]],[0,[]],[0,[[5,"1"]]],[0,[]],[0,[]],[0,[[2,"1"]]],[0,[]],[0,[[4,"1"]]],[0,[]],[0,[[5,"1"]]],[0,[]],[0,[]],[0,[[2,"1"]]],[0,[]],[0,[[4,"1"]]],[0,[]],[0,[[2,"1"]]],[0,[]],[0,[]],[0,[[2,"1"]]],[0,[]],[0,[[4,"1"]]],[0,[]],[0,[[2,"1"]]],[0,[]],[0,[]],[0,[[4,"1"]]],[0,[]],[0,[[2,"1"]]],[0,[]],[0,[[5,"1"]]],[0,[]],[0,[]],[0,[[2,"1"]]],[0,[]],[0,[[4,"1"]]],[0,[]],[0,[[5,"1"]]],[0,[]],[0,[]],[0,[[2,"1"]]],[0,[]],[0,[[4,"1"]]],[0,[]],[0,[[2,"1"]]],[0,[]],[0,[]],[0,[[2,"1"]]],[0,[]],[0,[[4,"1"]]],[0,[]],[0,[[2,"1"]]],[0,[]],[0,[]],[0,[[4,"1"]]],[0,[]],[0,[[2,"1"]]],[0,[]],[0,[[5,"1"]]],[0,[]],[0,[]],[0,[]],[1,[]],[0,[[5,"1"]]],[0,[[2,"1"],[5,"1"]]],[0,[]],[0,[[5,"1"],[7,"1"],[9,"1"]]],[0,[]],[0,[[2,"1"],[5,"1"]]],[0,[]],[0,[[4,"1"],[7,"1"],[9,"1"]]],[0,[[6,"1"]]],[0,[[5,"1"],[7,"1"]]],[0,[[7,"1"]]],[0,[[5,"1"],[7,"1"],[9,"1"]]],[0,[]],[0,[[2,"1"],[5,"1"]]],[0,[]],[0,[[4,"1"],[5,"1"],[7,"1"],[9,"1"]]],[0,[[7,"1"]]],[0,[[2,"1"],[6,"1"]]],[0,[]],[0,[[4,"1"],[6,"1"],[9,"1"]]],[0,[]],[0,[[4,"1"]]],[0,[]],[0,[[2,"1"],[4,"1"],[6,"1"],[9,"1"]]],[0,[]],[0,[[5,"1"],[6,"1"]]],[0,[[6,"1"]]],[0,[[5,"1"],[7,"1"],[9,"1"]]],[0,[]],[0,[[2,"1"],[5,"1"]]],[0,[]],[0,[[4,"1"],[7,"1"],[9,"1"]]],[0,[[5,"1"]]],[0,[[2,"1"],[5,"1"]]],[0,[]],[0,[[5,"1"],[7,"1"],[9,"1"]]],[0,[]],[0,[[2,"1"],[5,"1"]]],[0,[]],[0,[[4,"1"],[7,"1"],[9,"1"]]],[0,[[6,"1"]]],[0,[[5,"1"],[7,"1"]]],[0,[]],[0,[[5,"1"],[7,"1"],[9,"1"]]],[0,[[5,"1"]]],[0,[[2,"1"]]],[0,[[5,"1"]]],[0,[[4,"1"],[5,"1"],[7,"1"],[9,"1"]]],[0,[[7,"1"]]],[0,[[2,"1"],[9,"1"]]],[0,[[9,"1"]]],[0,[[6,"1"],[9,"1"]]],[0,[[8,"1"]]],[0,[[4,"1"],[7,"1"]]],[0,[]],[0,[[2,"1"],[6,"1"],[9,"1"]]],[0,[]],[0,[[5,"1"],[7,"1"]]],[0,[]],[0,[[5,"1"],[7,"1"],[9,"1"]]],[0,[[5,"1"]]],[0,[[2,"1"],[5,"1"]]],[0,[]],[0,[[4,"1"],[5,"1"],[7,"1"],[9,"1"]]],[0,[[7,"1"]]],[0,[[5,"1"],[9,"1"]]],[0,[]],[0,[[7,"1"],[9,"1"]]],[0,[]],[0,[[2,"1"],[8,"1"]]],[0,[]],[0,[[4,"1"],[7,"1"],[9,"1"]]],[0,[]],[0,[[2,"1"],[6,"1"]]],[0,[]],[0,[[4,"1"],[7,"1"],[9,"1"]]],[0,[[4,"1"]]],[0,[[2,"1"],[4,"1"]]],[0,[]],[0,[[4,"1"],[7,"1"],[9,"1"]]],[0,[[6,"1"]]],[0,[[2,"1"],[8,"1"]]],[0,[[8,"1"]]],[0,[[6,"1"],[8,"1"],[9,"1"]]],[0,[[8,"1"]]],[0,[[4,"1"],[7,"1"]]],[0,[[7,"1"]]],[0,[[2,"1"],[6,"1"],[9,"1"]]],[0,[[6,"1"]]],[0,[[5,"1"],[7,"1"]]],[0,[]],[0,[[5,"1"],[7,"1"],[9,"1"]]],[0,[[5,"1"]]],[0,[[2,"1"],[5,"1"]]],[0,[]],[0,[[4,"1"],[7,"1"],[9,"1"]]],[0,[[5,"1"]]],[0,[[5,"1"],[9,"1"]]],[0,[]],[0,[[7,"1"],[9,"1"]]],[0,[]],[0,[[2,"1"],[8,"1"]]],[0,[]],[0,[[4,"1"],[7,"1"],[9,"1"]]],[0,[]],[0,[[2,"1"],[6,"1"]]],[0,[]],[0,[[4,"1"],[7,"1"],[9,"1"]]],[0,[[4,"1"]]],[0,[[2,"1"],[4,"1"]]],[0,[]],[0,[[4,"1"],[7,"1"],[9,"1"]]],[0,[[6,"1"]]],[0,[[2,"1"],[8,"1"]]],[0,[[8,"1"]]],[0,[[6,"1"],[8,"1"],[9,"1"]]],[0,[[8,"1"]]],[0,[[4,"1"],[7,"1"]]],[0,[]],[0,[[2,"1"],[6,"1"],[9,"1"]]],[0,[]],[0,[[5,"1"],[7,"1"],[9,"1"]]],[0,[]],[0,[]],[0,[]],[1,[]],[0,[[5,"1"]]],[0,[[2,"1"],[5,"1"]]],[0,[]],[0,[[5,"1"],[7,"1"],[9,"1"]]],[0,[]],[0,[[2,"1"],[5,"1"]]],[0,[]],[0,[[4,"1"],[7,"1"],[9,"1"]]],[0,[[6,"1"]]],[0,[[5,"1"],[7,"1"]]],[0,[[7,"1"]]],[0,[[5,"1"],[7,"1"],[9,"1"]]],[0,[[5,"1"]]],[0,[[2,"1"],[5,"1"]]],[0,[]],[0,[[4,"1"],[5,"1"],[7,"1"],[9,"1"]]],[0,[[7,"1"]]],[0,[[2,"1"],[6,"1"]]],[0,[]],[0,[[4,"1"],[6,"1"],[9,"1"]]],[0,[]],[0,[[4,"1"]]],[0,[]],[0,[[2,"1"],[4,"1"],[6,"1"],[9,"1"]]],[0,[]],[0,[[5,"1"],[6,"1"]]],[0,[]],[0,[[5,"1"],[7,"1"],[9,"1"]]],[0,[]],[0,[[2,"1"],[5,"1"]]],[0,[]],[0,[[4,"1"],[5,"1"],[7,"1"],[9,"1"]]],[0,[[5,"1"]]],[0,[[2,"1"],[5,"1"]]],[0,[]],[0,[[5,"1"],[7,"1"],[9,"1"]]],[0,[]],[0,[[2,"1"],[5,"1"]]],[0,[]],[0,[[4,"1"],[7,"1"],[9,"1"]]],[0,[[6,"1"]]],[0,[[5,"1"],[7,"1"]]],[0,[]],[0,[[5,"1"],[7,"1"],[9,"1"]]],[0,[[5,"1"]]],[0,[[2,"1"]]],[0,[[5,"1"]]],[0,[[4,"1"],[5,"1"],[7,"1"],[9,"1"]]],[0,[[7,"1"]]],[0,[[2,"1"],[9,"1"]]],[0,[[9,"1"]]],[0,[[6,"1"],[9,"1"]]],[0,[[8,"1"]]],[0,[[4,"1"],[7,"1"]]],[0,[[7,"1"]]],[0,[[2,"1"],[6,"1"],[9,"1"]]],[0,[]],[0,[[5,"1"],[7,"1"]]],[0,[]],[0,[[5,"1"],[7,"1"],[9,"1"]]],[0,[]],[0,[[2,"1"],[5,"1"]]],[0,[]],[0,[[4,"1"],[5,"1"],[7,"1"],[9,"1"]]],[0,[[5,"1"]]],[0,[[5,"1"],[9,"1"]]],[0,[]],[0,[[7,"1"],[9,"1"]]],[0,[]],[0,[[2,"1"],[8,"1"]]],[0,[]],[0,[[4,"1"],[7,"1"],[9,"1"]]],[0,[]],[0,[[2,"1"],[6,"1"]]],[0,[]],[0,[[4,"1"],[7,"1"],[9,"1"]]],[0,[[4,"1"]]],[0,[[2,"1"]]],[0,[[4,"1"]]],[0,[[4,"1"],[7,"1"],[9,"1"]]],[0,[[6,"1"]]],[0,[[5,"1"],[9,"1"]]],[0,[]],[0,[[7,"1"],[9,"1"]]],[0,[]],[0,[[2,"1"],[8,"1"]]],[0,[]],[0,[[4,"1"],[7,"1"],[9,"1"]]],[0,[]],[0,[[2,"1"],[6,"1"]]],[0,[]],[0,[[4,"1"],[7,"1"],[9,"1"]]],[0,[[4,"1"]]],[0,[[2,"1"]]],[0,[[4,"1"]]],[0,[[4,"1"],[7,"1"],[9,"1"]]],[0,[[6,"1"]]],[0,[[5,"1"],[9,"1"]]],[0,[]],[0,[[7,"1"],[9,"1"]]],[0,[]],[0,[[2,"1"],[8,"1"]]],[0,[]],[0,[[4,"1"],[7,"1"],[9,"1"]]],[0,[]],[0,[[5,"1"],[9,"1"]]],[0,[]],[0,[[7,"1"],[9,"1"]]],[0,[]],[0,[[2,"1"],[8,"1"]]],[0,[]],[0,[[4,"1"],[7,"1"],[9,"1"]]],[0,[]],[0,[[5,"1"],[9,"1"]]],[0,[]],[0,[[7,"1"],[9,"1"]]],[0,[]],[0,[[5,"1"],[9,"1"]]],[0,[]],[0,[[7,"1"],[9,"1"]]],[0,[]],[0,[[5,"1"],[9,"1"]]],[0,[]],[0,[[5,"1"],[9,"1"]]],[0,[]],[0,[[5,"1"],[9,"1"]]],[0,[[5,"1"],[9,"1"]]],[0,[[5,"1"],[9,"1"]]],[0,[[5,"1"]]],[0,[[2,"1"],[5,"1"]]],[0,[]],[0,[[5,"1"],[7,"1"],[9,"1"]]],[0,[]],[0,[[2,"1"],[5,"1"]]],[0,[]],[0,[[4,"1"],[7,"1"],[9,"1"]]],[0,[[6,"1"]]],[0,[[5,"1"],[7,"1"]]],[0,[[7,"1"]]],[0,[[5,"1"],[7,"1"],[9,"1"]]],[0,[[5,"1"]]],[0,[[2,"1"],[5,"1"]]],[0,[]],[0,[[4,"1"],[5,"1"],[7,"1"],[9,"1"]]],[0,[[7,"1"]]],[0,[[2,"1"],[6,"1"]]],[0,[]],[0,[[4,"1"],[6,"1"],[9,"1"]]],[0,[]],[0,[[4,"1"]]],[0,[]],[0,[[2,"1"],[4,"1"],[6,"1"],[9,"1"]]],[0,[]],[0,[[5,"1"],[6,"1"]]],[0,[]],[0,[[5,"1"],[7,"1"],[9,"1"]]],[0,[]],[0,[[2,"1"],[5,"1"]]],[0,[]],[0,[[4,"1"],[5,"1"],[7,"1"],[9,"1"]]],[0,[[5,"1"]]],[0,[[2,"1"],[5,"1"]]],[0,[]],[0,[[5,"1"],[7,"1"],[9,"1"]]],[0,[]],[0,[[2,"1"],[5,"1"]]],[0,[]],[0,[[4,"1"],[7,"1"],[9,"1"]]],[0,[[6,"1"]]],[0,[[5,"1"],[7,"1"]]],[0,[]],[0,[[5,"1"],[7,"1"],[9,"1"]]],[0,[[5,"1"]]],[0,[[2,"1"]]],[0,[[5,"1"]]],[0,[[4,"1"],[5,"1"],[7,"1"],[9,"1"]]],[0,[[7,"1"]]],[0,[[2,"1"],[9,"1"]]],[0,[[9,"1"]]],[0,[[6,"1"],[9,"1"]]],[0,[[8,"1"]]],[0,[[4,"1"],[7,"1"]]],[0,[[7,"1"]]],[0,[[2,"1"],[6,"1"],[9,"1"]]],[0,[]],[0,[[5,"1"],[7,"1"]]],[0,[]],[0,[[5,"1"],[7,"1"],[9,"1"]]],[0,[]],[0,[[2,"1"],[5,"1"]]],[0,[]],[0,[[4,"1"],[5,"1"],[7,"1"],[9,"1"]]],[0,[[5,"1"]]],[0,[[5,"1"],[9,"1"]]],[0,[]],[0,[[7,"1"],[9,"1"]]],[0,[]],[0,[[2,"1"],[8,"1"]]],[0,[]],[0,[[4,"1"],[7,"1"],[9,"1"]]],[0,[]],[0,[[2,"1"],[6,"1"]]],[0,[]],[0,[[4,"1"],[7,"1"],[9,"1"]]],[0,[[4,"1"]]],[0,[[2,"1"]]],[0,[[4,"1"]]],[0,[[4,"1"],[7,"1"],[9,"1"]]],[0,[[6,"1"]]],[0,[[2,"1"],[8,"1"]]],[0,[[8,"1"]]],[0,[[6,"1"],[8,"1"],[9,"1"]]],[0,[[8,"1"]]],[0,[[4,"1"],[7,"1"]]],[0,[[7,"1"]]],[0,[[2,"1"],[6,"1"],[9,"1"]]],[0,[[6,"1"]]],[0,[[5,"1"],[7,"1"]]],[0,[]],[0,[[5,"1"],[7,"1"],[9,"1"]]],[0,[[5,"1"]]],[0,[[2,"1"]]],[0,[]],[0,[[4,"1"],[7,"1"],[9,"1"]]],[0,[[5,"1"]]],[0,[[5,"1"],[9,"1"]]],[0,[]],[0,[[7,"1"],[9,"1"]]],[0,[]],[0,[[2,"1"],[8,"1"]]],[0,[]],[0,[[4,"1"],[7,"1"],[9,"1"]]],[0,[]],[0,[[2,"1"],[6,"1"]]],[0,[]],[0,[[4,"1"],[7,"1"],[9,"1"]]],[0,[]],[0,[[2,"1"],[4,"1"]]],[0,[]],[0,[[4,"1"],[7,"1"],[9,"1"]]],[0,[[6,"1"]]],[0,[[2,"1"],[8,"1"]]],[0,[[8,"1"]]],[0,[[6,"1"],[8,"1"],[9,"1"]]],[0,[[8,"1"]]],[0,[[4,"1"],[7,"1"]]],[0,[]],[0,[[2,"1"],[6,"1"],[9,"1"]]],[0,[]],[0,[[5,"1"],[7,"1"],[9,"1"]]],[0,[]],[0,[[5,"1"]]],[0,[[5,"1"]]],[0,[]],[0,[]],[0,[[5,"1"]]],[0,[[2,"1"],[5,"1"]]],[0,[]],[0,[[5,"1"],[7,"1"],[9,"1"]]],[0,[]],[0,[[2,"1"],[5,"1"]]],[0,[]],[0,[[4,"1"],[7,"1"],[9,"1"]]],[0,[[6,"1"]]],[0,[[5,"1"],[7,"1"]]],[0,[[7,"1"]]],[0,[[5,"1"],[7,"1"],[9,"1"]]],[0,[[5,"1"]]],[0,[[2,"1"],[5,"1"]]],[0,[]],[0,[[4,"1"],[5,"1"],[7,"1"],[9,"1"]]],[0,[[7,"1"]]],[0,[[2,"1"],[6,"1"]]],[0,[]],[0,[[4,"1"],[6,"1"],[9,"1"]]],[0,[]],[0,[[4,"1"]]],[0,[]],[0,[[2,"1"],[4,"1"],[6,"1"],[9,"1"]]],[0,[]],[0,[[5,"1"],[6,"1"]]],[0,[]],[0,[[5,"1"],[7,"1"],[9,"1"]]],[0,[]],[0,[[2,"1"],[5,"1"]]],[0,[]],[0,[[4,"1"],[5,"1"],[7,"1"],[9,"1"]]],[0,[[5,"1"]]],[0,[[2,"1"],[5,"1"]]],[0,[]],[0,[[5,"1"],[7,"1"],[9,"1"]]],[0,[]],[0,[[2,"1"],[5,"1"]]],[0,[]],[0,[[4,"1"],[7,"1"],[9,"1"]]],[0,[[6,"1"]]],[0,[[5,"1"],[7,"1"]]],[0,[]],[0,[[5,"1"],[7,"1"],[9,"1"]]],[0,[[5,"1"]]],[0,[[2,"1"]]],[0,[[5,"1"]]],[0,[[4,"1"],[5,"1"],[7,"1"],[9,"1"]]],[0,[[7,"1"]]],[0,[[2,"1"],[9,"1"]]],[0,[[9,"1"]]],[0,[[6,"1"],[9,"1"]]],[0,[[8,"1"]]],[0,[[4,"1"],[7,"1"]]],[0,[[7,"1"]]],[0,[[2,"1"],[6,"1"],[9,"1"]]],[0,[]],[0,[[5,"1"],[7,"1"]]],[0,[]],[0,[[5,"1"],[7,"1"],[9,"1"]]],[0,[]],[0,[[2,"1"],[5,"1"]]],[0,[]],[0,[[4,"1"],[5,"1"],[7,"1"],[9,"1"]]],[0,[[5,"1"]]],[0,[[5,"1"],[9,"1"]]],[0,[]],[0,[[7,"1"],[9,"1"]]],[0,[]],[0,[[2,"1"],[8,"1"]]],[0,[]],[0,[[4,"1"],[7,"1"],[9,"1"]]],[0,[]],[0,[[2,"1"],[6,"1"]]],[0,[]],[0,[[4,"1"],[7,"1"],[9,"1"]]],[0,[[4,"1"]]],[0,[[2,"1"]]],[0,[[4,"1"]]],[0,[[4,"1"],[7,"1"],[9,"1"]]],[0,[[6,"1"]]],[0,[[2,"1"],[8,"1"]]],[0,[[8,"1"]]],[0,[[6,"1"],[8,"1"],[9,"1"]]],[0,[[8,"1"]]],[0,[[4,"1"],[7,"1"]]],[0,[[7,"1"]]],[0,[[2,"1"],[6,"1"],[9,"1"]]],[0,[[6,"1"]]],[0,[[5,"1"],[7,"1"]]],[0,[]],[0,[[5,"1"],[7,"1"],[9,"1"]]],[0,[[5,"1"]]],[0,[[2,"1"]]],[0,[]],[0,[[4,"1"],[7,"1"],[9,"1"]]],[0,[[5,"1"]]],[0,[[5,"1"],[9,"1"]]],[0,[]],[0,[[7,"1"],[9,"1"]]],[0,[]],[0,[[2,"1"],[8,"1"]]],[0,[]],[0,[[4,"1"],[7,"1"],[9,"1"]]],[0,[]],[0,[[2,"1"],[6,"1"]]],[0,[]],[0,[[4,"1"],[7,"1"],[9,"1"]]],[0,[]],[0,[[2,"1"],[4,"1"]]],[0,[]],[0,[[4,"1"],[7,"1"],[9,"1"]]],[0,[[6,"1"]]],[0,[[2,"1"],[8,"1"]]],[0,[[8,"1"]]],[0,[[6,"1"],[8,"1"],[9,"1"]]],[0,[[8,"1"]]],[0,[[4,"1"],[7,"1"]]],[0,[]],[0,[[2,"1"],[6,"1"],[9,"1"]]],[0,[]],[0,[[5,"1"],[7,"1"],[9,"1"]]],[0,[]],[0,[[5,"1"]]],[0,[[5,"1"]]],[0,[]],[0,[]],[1,[]],[0,[[5,"1"]]],[0,[]],[0,[[7,"1"],[9,"1"]]],[0,[]],[0,[[2,"1"]]],[0,[]],[0,[[4,"1"],[7,"1"],[9,"1"]]],[0,[]],[0,[[5,"1"]]],[0,[]],[0,[[7,"1"],[9,"1"]]],[0,[]],[0,[[2,"1"]]],[0,[]],[0,[[4,"1"],[7,"1"],[9,"1"]]],[0,[]],[0,[[2,"1"]]],[0,[]],[0,[[6,"1"],[9,"1"]]],[0,[]],[0,[[4,"1"]]],[0,[]],[0,[[2,"1"],[6,"1"],[9,"1"]]],[0,[]],[0,[[5,"1"]]],[0,[]],[0,[[7,"1"],[9,"1"]]],[0,[]],[0,[[2,"1"]]],[0,[]],[0,[[4,"1"],[7,"1"],[9,"1"]]],[0,[]],[0,[[5,"1"]]],[0,[]],[0,[[7,"1"],[9,"1"]]],[0,[]],[0,[[2,"1"]]],[0,[]],[0,[[4,"1"],[7,"1"],[9,"1"]]],[0,[]],[0,[[5,"1"]]],[0,[]],[0,[[7,"1"],[9,"1"]]],[0,[]],[0,[[2,"1"]]],[0,[]],[0,[[4,"1"],[7,"1"],[9,"1"]]],[0,[]],[0,[[2,"1"]]],[0,[]],[0,[[6,"1"],[9,"1"]]],[0,[]],[0,[[4,"1"]]],[0,[]],[0,[[2,"1"],[6,"1"],[9,"1"]]],[0,[]],[0,[[5,"1"]]],[0,[]],[0,[[7,"1"],[9,"1"]]],[0,[]],[0,[[2,"1"]]],[0,[]],[0,[[4,"1"],[7,"1"],[9,"1"]]],[0,[]],[0,[[5,"1"]]],[0,[]],[0,[[7,"1"],[9,"1"]]],[0,[]],[0,[[2,"1"]]],[0,[]],[0,[[4,"1"],[7,"1"],[9,"1"]]],[0,[]],[0,[[2,"1"]]],[0,[]],[0,[[7,"1"],[9,"1"]]],[0,[]],[0,[[2,"1"]]],[0,[]],[0,[[4,"1"],[7,"1"],[9,"1"]]],[0,[]],[0,[[2,"1"]]],[0,[]],[0,[[6,"1"],[9,"1"]]],[0,[]],[0,[[4,"1"]]],[0,[]],[0,[[2,"1"],[6,"1"],[9,"1"]]],[0,[]],[0,[[5,"1"]]],[0,[]],[0,[[7,"1"],[9,"1"]]],[0,[]],[0,[[2,"1"]]],[0,[]],[0,[[4,"1"],[7,"1"],[9,"1"]]],[0,[]],[0,[[5,"1"]]],[0,[]],[0,[[7,"1"],[9,"1"]]],[0,[]],[0,[[2,"1"]]],[0,[]],[0,[[4,"1"],[7,"1"],[9,"1"]]],[0,[]],[0,[[2,"1"]]],[0,[]],[0,[[7,"1"],[9,"1"]]],[0,[]],[0,[[2,"1"]]],[0,[]],[0,[[4,"1"],[7,"1"],[9,"1"]]],[0,[]],[0,[[2,"1"]]],[0,[]],[0,[[6,"1"],[9,"1"]]],[0,[]],[0,[[4,"1"]]],[0,[]],[0,[[2,"1"],[6,"1"],[9,"1"]]],[0,[]],[0,[[5,"1"],[7,"1"],[9,"1"]]]],"id":"962492a7-7382-a9be-de1f","pitchLevel":0,"isComposed":true,"bitsPerPage":16,"isEncrypted":false,"songNotes":[{"key":"1Key5","time":100},{"key":"1Key7","time":350},{"key":"1Key9","time":350},{"key":"1Key2","time":600},{"key":"1Key7","time":850},{"key":"1Key9","time":850},{"key":"1Key5","time":1100},{"key":"1Key7","time":1350},{"key":"1Key9","time":1350},{"key":"1Key2","time":1600},{"key":"1Key4","time":1850},{"key":"1Key7","time":1850},{"key":"1Key9","time":1850},{"key":"1Key5","time":2100},{"key":"1Key7","time":2350},{"key":"1Key9","time":2350},{"key":"1Key2","time":2600},{"key":"1Key7","time":2850},{"key":"1Key9","time":2850},{"key":"1Key5","time":3100},{"key":"1Key7","time":3350},{"key":"1Key9","time":3350},{"key":"1Key2","time":3600},{"key":"1Key4","time":3850},{"key":"1Key7","time":3850},{"key":"1Key9","time":3850},{"key":"1Key5","time":4100},{"key":"1Key7","time":4350},{"key":"1Key9","time":4350},{"key":"1Key2","time":4600},{"key":"1Key7","time":4850},{"key":"1Key9","time":4850},{"key":"1Key5","time":5100},{"key":"1Key7","time":5350},{"key":"1Key9","time":5350},{"key":"1Key2","time":5600},{"key":"1Key4","time":5850},{"key":"1Key7","time":5850},{"key":"1Key9","time":5850},{"key":"1Key5","time":6100},{"key":"1Key7","time":6350},{"key":"1Key9","time":6350},{"key":"1Key2","time":6600},{"key":"1Key7","time":6850},{"key":"1Key9","time":6850},{"key":"1Key5","time":7100},{"key":"1Key7","time":7350},{"key":"1Key9","time":7350},{"key":"1Key2","time":7600},{"key":"1Key4","time":7850},{"key":"1Key7","time":7850},{"key":"1Key9","time":7850},{"key":"1Key5","time":8100},{"key":"1Key7","time":8350},{"key":"1Key9","time":8350},{"key":"1Key2","time":8600},{"key":"1Key7","time":8850},{"key":"1Key9","time":8850},{"key":"1Key5","time":9100},{"key":"1Key7","time":9350},{"key":"1Key9","time":9350},{"key":"1Key2","time":9600},{"key":"1Key4","time":9850},{"key":"1Key7","time":9850},{"key":"1Key9","time":9850},{"key":"1Key5","time":10100},{"key":"1Key7","time":10350},{"key":"1Key9","time":10350},{"key":"1Key2","time":10600},{"key":"1Key7","time":10850},{"key":"1Key9","time":10850},{"key":"1Key5","time":11100},{"key":"1Key7","time":11350},{"key":"1Key9","time":11350},{"key":"1Key2","time":11600},{"key":"1Key4","time":11850},{"key":"1Key7","time":11850},{"key":"1Key9","time":11850},{"key":"1Key5","time":12100},{"key":"1Key7","time":12350},{"key":"1Key9","time":12350},{"key":"1Key2","time":12600},{"key":"1Key7","time":12850},{"key":"1Key9","time":12850},{"key":"1Key5","time":13100},{"key":"1Key7","time":13350},{"key":"1Key9","time":13350},{"key":"1Key2","time":13600},{"key":"1Key4","time":13850},{"key":"1Key7","time":13850},{"key":"1Key9","time":13850},{"key":"1Key5","time":14100},{"key":"1Key7","time":14350},{"key":"1Key9","time":14350},{"key":"1Key2","time":14600},{"key":"1Key7","time":14850},{"key":"1Key9","time":14850},{"key":"1Key5","time":15100},{"key":"1Key7","time":15100},{"key":"1Key9","time":15100},{"key":"1Key5","time":15662},{"key":"1Key2","time":15787},{"key":"1Key5","time":15787},{"key":"1Key5","time":16037},{"key":"1Key7","time":16037},{"key":"1Key9","time":16037},{"key":"1Key2","time":16287},{"key":"1Key5","time":16287},{"key":"1Key4","time":16537},{"key":"1Key7","time":16537},{"key":"1Key9","time":16537},{"key":"1Key6","time":16662},{"key":"1Key5","time":16787},{"key":"1Key7","time":16787},{"key":"1Key7","time":16912},{"key":"1Key5","time":17037},{"key":"1Key7","time":17037},{"key":"1Key9","time":17037},{"key":"1Key5","time":17162},{"key":"1Key2","time":17287},{"key":"1Key5","time":17287},{"key":"1Key4","time":17537},{"key":"1Key5","time":17537},{"key":"1Key7","time":17537},{"key":"1Key9","time":17537},{"key":"1Key7","time":17662},{"key":"1Key2","time":17787},{"key":"1Key6","time":17787},{"key":"1Key4","time":18037},{"key":"1Key6","time":18037},{"key":"1Key9","time":18037},{"key":"1Key4","time":18287},{"key":"1Key2","time":18537},{"key":"1Key4","time":18537},{"key":"1Key6","time":18537},{"key":"1Key9","time":18537},{"key":"1Key5","time":18787},{"key":"1Key6","time":18787},{"key":"1Key5","time":19037},{"key":"1Key7","time":19037},{"key":"1Key9","time":19037},{"key":"1Key2","time":19287},{"key":"1Key5","time":19287},{"key":"1Key4","time":19537},{"key":"1Key5","time":19537},{"key":"1Key7","time":19537},{"key":"1Key9","time":19537},{"key":"1Key5","time":19662},{"key":"1Key2","time":19787},{"key":"1Key5","time":19787},{"key":"1Key5","time":20037},{"key":"1Key7","time":20037},{"key":"1Key9","time":20037},{"key":"1Key2","time":20287},{"key":"1Key5","time":20287},{"key":"1Key4","time":20537},{"key":"1Key7","time":20537},{"key":"1Key9","time":20537},{"key":"1Key6","time":20662},{"key":"1Key5","time":20787},{"key":"1Key7","time":20787},{"key":"1Key5","time":21037},{"key":"1Key7","time":21037},{"key":"1Key9","time":21037},{"key":"1Key5","time":21162},{"key":"1Key2","time":21287},{"key":"1Key5","time":21412},{"key":"1Key4","time":21537},{"key":"1Key5","time":21537},{"key":"1Key7","time":21537},{"key":"1Key9","time":21537},{"key":"1Key7","time":21662},{"key":"1Key2","time":21787},{"key":"1Key9","time":21787},{"key":"1Key9","time":21912},{"key":"1Key6","time":22037},{"key":"1Key9","time":22037},{"key":"1Key8","time":22162},{"key":"1Key4","time":22287},{"key":"1Key7","time":22287},{"key":"1Key7","time":22412},{"key":"1Key2","time":22537},{"key":"1Key6","time":22537},{"key":"1Key9","time":22537},{"key":"1Key5","time":22787},{"key":"1Key7","time":22787},{"key":"1Key5","time":23037},{"key":"1Key7","time":23037},{"key":"1Key9","time":23037},{"key":"1Key2","time":23287},{"key":"1Key5","time":23287},{"key":"1Key4","time":23537},{"key":"1Key5","time":23537},{"key":"1Key7","time":23537},{"key":"1Key9","time":23537},{"key":"1Key5","time":23662},{"key":"1Key5","time":23787},{"key":"1Key9","time":23787},{"key":"1Key7","time":24037},{"key":"1Key9","time":24037},{"key":"1Key2","time":24287},{"key":"1Key8","time":24287},{"key":"1Key4","time":24537},{"key":"1Key7","time":24537},{"key":"1Key9","time":24537},{"key":"1Key2","time":24787},{"key":"1Key6","time":24787},{"key":"1Key4","time":25037},{"key":"1Key7","time":25037},{"key":"1Key9","time":25037},{"key":"1Key4","time":25162},{"key":"1Key2","time":25287},{"key":"1Key4","time":25412},{"key":"1Key4","time":25537},{"key":"1Key7","time":25537},{"key":"1Key9","time":25537},{"key":"1Key6","time":25662},{"key":"1Key2","time":25787},{"key":"1Key8","time":25787},{"key":"1Key8","time":25912},{"key":"1Key6","time":26037},{"key":"1Key8","time":26037},{"key":"1Key9","time":26037},{"key":"1Key8","time":26162},{"key":"1Key4","time":26287},{"key":"1Key7","time":26287},{"key":"1Key7","time":26412},{"key":"1Key2","time":26537},{"key":"1Key6","time":26537},{"key":"1Key9","time":26537},{"key":"1Key6","time":26662},{"key":"1Key5","time":26787},{"key":"1Key7","time":26787},{"key":"1Key5","time":27037},{"key":"1Key7","time":27037},{"key":"1Key9","time":27037},{"key":"1Key5","time":27162},{"key":"1Key2","time":27287},{"key":"1Key4","time":27537},{"key":"1Key7","time":27537},{"key":"1Key9","time":27537},{"key":"1Key5","time":27662},{"key":"1Key5","time":27787},{"key":"1Key9","time":27787},{"key":"1Key7","time":28037},{"key":"1Key9","time":28037},{"key":"1Key2","time":28287},{"key":"1Key8","time":28287},{"key":"1Key4","time":28537},{"key":"1Key7","time":28537},{"key":"1Key9","time":28537},{"key":"1Key2","time":28787},{"key":"1Key6","time":28787},{"key":"1Key4","time":29037},{"key":"1Key7","time":29037},{"key":"1Key9","time":29037},{"key":"1Key2","time":29287},{"key":"1Key4","time":29287},{"key":"1Key4","time":29537},{"key":"1Key7","time":29537},{"key":"1Key9","time":29537},{"key":"1Key6","time":29662},{"key":"1Key2","time":29787},{"key":"1Key8","time":29787},{"key":"1Key8","time":29912},{"key":"1Key6","time":30037},{"key":"1Key8","time":30037},{"key":"1Key9","time":30037},{"key":"1Key8","time":30162},{"key":"1Key4","time":30287},{"key":"1Key7","time":30287},{"key":"1Key2","time":30537},{"key":"1Key6","time":30537},{"key":"1Key9","time":30537},{"key":"1Key5","time":30787},{"key":"1Key7","time":30787},{"key":"1Key9","time":30787},{"key":"1Key5","time":31037},{"key":"1Key5","time":31162},{"key":"1Key5","time":31537},{"key":"1Key2","time":31662},{"key":"1Key5","time":31662},{"key":"1Key5","time":31912},{"key":"1Key7","time":31912},{"key":"1Key9","time":31912},{"key":"1Key2","time":32162},{"key":"1Key5","time":32162},{"key":"1Key4","time":32412},{"key":"1Key7","time":32412},{"key":"1Key9","time":32412},{"key":"1Key6","time":32537},{"key":"1Key5","time":32662},{"key":"1Key7","time":32662},{"key":"1Key7","time":32787},{"key":"1Key5","time":32912},{"key":"1Key7","time":32912},{"key":"1Key9","time":32912},{"key":"1Key5","time":33037},{"key":"1Key2","time":33162},{"key":"1Key5","time":33162},{"key":"1Key4","time":33412},{"key":"1Key5","time":33412},{"key":"1Key7","time":33412},{"key":"1Key9","time":33412},{"key":"1Key7","time":33537},{"key":"1Key2","time":33662},{"key":"1Key6","time":33662},{"key":"1Key4","time":33912},{"key":"1Key6","time":33912},{"key":"1Key9","time":33912},{"key":"1Key4","time":34162},{"key":"1Key2","time":34412},{"key":"1Key4","time":34412},{"key":"1Key6","time":34412},{"key":"1Key9","time":34412},{"key":"1Key5","time":34662},{"key":"1Key6","time":34662},{"key":"1Key5","time":34912},{"key":"1Key7","time":34912},{"key":"1Key9","time":34912},{"key":"1Key2","time":35162},{"key":"1Key5","time":35162},{"key":"1Key4","time":35412},{"key":"1Key5","time":35412},{"key":"1Key7","time":35412},{"key":"1Key9","time":35412},{"key":"1Key5","time":35537},{"key":"1Key2","time":35662},{"key":"1Key5","time":35662},{"key":"1Key5","time":35912},{"key":"1Key7","time":35912},{"key":"1Key9","time":35912},{"key":"1Key2","time":36162},{"key":"1Key5","time":36162},{"key":"1Key4","time":36412},{"key":"1Key7","time":36412},{"key":"1Key9","time":36412},{"key":"1Key6","time":36537},{"key":"1Key5","time":36662},{"key":"1Key7","time":36662},{"key":"1Key5","time":36912},{"key":"1Key7","time":36912},{"key":"1Key9","time":36912},{"key":"1Key5","time":37037},{"key":"1Key2","time":37162},{"key":"1Key5","time":37287},{"key":"1Key4","time":37412},{"key":"1Key5","time":37412},{"key":"1Key7","time":37412},{"key":"1Key9","time":37412},{"key":"1Key7","time":37537},{"key":"1Key2","time":37662},{"key":"1Key9","time":37662},{"key":"1Key9","time":37787},{"key":"1Key6","time":37912},{"key":"1Key9","time":37912},{"key":"1Key8","time":38037},{"key":"1Key4","time":38162},{"key":"1Key7","time":38162},{"key":"1Key7","time":38287},{"key":"1Key2","time":38412},{"key":"1Key6","time":38412},{"key":"1Key9","time":38412},{"key":"1Key5","time":38662},{"key":"1Key7","time":38662},{"key":"1Key5","time":38912},{"key":"1Key7","time":38912},{"key":"1Key9","time":38912},{"key":"1Key2","time":39162},{"key":"1Key5","time":39162},{"key":"1Key4","time":39412},{"key":"1Key5","time":39412},{"key":"1Key7","time":39412},{"key":"1Key9","time":39412},{"key":"1Key5","time":39537},{"key":"1Key5","time":39662},{"key":"1Key9","time":39662},{"key":"1Key7","time":39912},{"key":"1Key9","time":39912},{"key":"1Key2","time":40162},{"key":"1Key8","time":40162},{"key":"1Key4","time":40412},{"key":"1Key7","time":40412},{"key":"1Key9","time":40412},{"key":"1Key2","time":40662},{"key":"1Key6","time":40662},{"key":"1Key4","time":40912},{"key":"1Key7","time":40912},{"key":"1Key9","time":40912},{"key":"1Key4","time":41037},{"key":"1Key2","time":41162},{"key":"1Key4","time":41287},{"key":"1Key4","time":41412},{"key":"1Key7","time":41412},{"key":"1Key9","time":41412},{"key":"1Key6","time":41537},{"key":"1Key2","time":41662},{"key":"1Key8","time":41662},{"key":"1Key8","time":41787},{"key":"1Key6","time":41912},{"key":"1Key8","time":41912},{"key":"1Key9","time":41912},{"key":"1Key8","time":42037},{"key":"1Key4","time":42162},{"key":"1Key7","time":42162},{"key":"1Key7","time":42287},{"key":"1Key2","time":42412},{"key":"1Key6","time":42412},{"key":"1Key9","time":42412},{"key":"1Key6","time":42537},{"key":"1Key5","time":42662},{"key":"1Key7","time":42662},{"key":"1Key5","time":42912},{"key":"1Key7","time":42912},{"key":"1Key9","time":42912},{"key":"1Key5","time":43037},{"key":"1Key2","time":43162},{"key":"1Key4","time":43412},{"key":"1Key7","time":43412},{"key":"1Key9","time":43412},{"key":"1Key5","time":43537},{"key":"1Key5","time":43662},{"key":"1Key9","time":43662},{"key":"1Key7","time":43912},{"key":"1Key9","time":43912},{"key":"1Key2","time":44162},{"key":"1Key8","time":44162},{"key":"1Key4","time":44412},{"key":"1Key7","time":44412},{"key":"1Key9","time":44412},{"key":"1Key2","time":44662},{"key":"1Key6","time":44662},{"key":"1Key4","time":44912},{"key":"1Key7","time":44912},{"key":"1Key9","time":44912},{"key":"1Key2","time":45162},{"key":"1Key4","time":45162},{"key":"1Key4","time":45412},{"key":"1Key7","time":45412},{"key":"1Key9","time":45412},{"key":"1Key6","time":45537},{"key":"1Key2","time":45662},{"key":"1Key8","time":45662},{"key":"1Key8","time":45787},{"key":"1Key6","time":45912},{"key":"1Key8","time":45912},{"key":"1Key9","time":45912},{"key":"1Key8","time":46037},{"key":"1Key4","time":46162},{"key":"1Key7","time":46162},{"key":"1Key2","time":46412},{"key":"1Key6","time":46412},{"key":"1Key9","time":46412},{"key":"1Key5","time":46662},{"key":"1Key7","time":46662},{"key":"1Key9","time":46662},{"key":"1Key5","time":46912},{"key":"1Key5","time":47037},{"key":"1Key5","time":47474},{"key":"1Key2","time":47849},{"key":"1Key4","time":48099},{"key":"1Key5","time":48349},{"key":"1Key2","time":48724},{"key":"1Key4","time":48974},{"key":"1Key2","time":49224},{"key":"1Key4","time":49599},{"key":"1Key2","time":49849},{"key":"1Key5","time":50099},{"key":"1Key2","time":50474},{"key":"1Key4","time":50724},{"key":"1Key5","time":50974},{"key":"1Key2","time":51349},{"key":"1Key4","time":51599},{"key":"1Key5","time":51849},{"key":"1Key2","time":52224},{"key":"1Key4","time":52474},{"key":"1Key2","time":52724},{"key":"1Key4","time":53099},{"key":"1Key2","time":53349},{"key":"1Key5","time":53599},{"key":"1Key2","time":53974},{"key":"1Key4","time":54224},{"key":"1Key5","time":54474},{"key":"1Key2","time":54849},{"key":"1Key4","time":55099},{"key":"1Key2","time":55349},{"key":"1Key2","time":55724},{"key":"1Key4","time":55974},{"key":"1Key2","time":56224},{"key":"1Key4","time":56599},{"key":"1Key2","time":56849},{"key":"1Key5","time":57099},{"key":"1Key2","time":57474},{"key":"1Key4","time":57724},{"key":"1Key5","time":57974},{"key":"1Key2","time":58349},{"key":"1Key4","time":58599},{"key":"1Key2","time":58849},{"key":"1Key2","time":59224},{"key":"1Key4","time":59474},{"key":"1Key2","time":59724},{"key":"1Key4","time":60099},{"key":"1Key2","time":60349},{"key":"1Key5","time":60599},{"key":"1Key5","time":61161},{"key":"1Key2","time":61286},{"key":"1Key5","time":61286},{"key":"1Key5","time":61536},{"key":"1Key7","time":61536},{"key":"1Key9","time":61536},{"key":"1Key2","time":61786},{"key":"1Key5","time":61786},{"key":"1Key4","time":62036},{"key":"1Key7","time":62036},{"key":"1Key9","time":62036},{"key":"1Key6","time":62161},{"key":"1Key5","time":62286},{"key":"1Key7","time":62286},{"key":"1Key7","time":62411},{"key":"1Key5","time":62536},{"key":"1Key7","time":62536},{"key":"1Key9","time":62536},{"key":"1Key2","time":62786},{"key":"1Key5","time":62786},{"key":"1Key4","time":63036},{"key":"1Key5","time":63036},{"key":"1Key7","time":63036},{"key":"1Key9","time":63036},{"key":"1Key7","time":63161},{"key":"1Key2","time":63286},{"key":"1Key6","time":63286},{"key":"1Key4","time":63536},{"key":"1Key6","time":63536},{"key":"1Key9","time":63536},{"key":"1Key4","time":63786},{"key":"1Key2","time":64036},{"key":"1Key4","time":64036},{"key":"1Key6","time":64036},{"key":"1Key9","time":64036},{"key":"1Key5","time":64286},{"key":"1Key6","time":64286},{"key":"1Key6","time":64411},{"key":"1Key5","time":64536},{"key":"1Key7","time":64536},{"key":"1Key9","time":64536},{"key":"1Key2","time":64786},{"key":"1Key5","time":64786},{"key":"1Key4","time":65036},{"key":"1Key7","time":65036},{"key":"1Key9","time":65036},{"key":"1Key5","time":65161},{"key":"1Key2","time":65286},{"key":"1Key5","time":65286},{"key":"1Key5","time":65536},{"key":"1Key7","time":65536},{"key":"1Key9","time":65536},{"key":"1Key2","time":65786},{"key":"1Key5","time":65786},{"key":"1Key4","time":66036},{"key":"1Key7","time":66036},{"key":"1Key9","time":66036},{"key":"1Key6","time":66161},{"key":"1Key5","time":66286},{"key":"1Key7","time":66286},{"key":"1Key5","time":66536},{"key":"1Key7","time":66536},{"key":"1Key9","time":66536},{"key":"1Key5","time":66661},{"key":"1Key2","time":66786},{"key":"1Key5","time":66911},{"key":"1Key4","time":67036},{"key":"1Key5","time":67036},{"key":"1Key7","time":67036},{"key":"1Key9","time":67036},{"key":"1Key7","time":67161},{"key":"1Key2","time":67286},{"key":"1Key9","time":67286},{"key":"1Key9","time":67411},{"key":"1Key6","time":67536},{"key":"1Key9","time":67536},{"key":"1Key8","time":67661},{"key":"1Key4","time":67786},{"key":"1Key7","time":67786},{"key":"1Key2","time":68036},{"key":"1Key6","time":68036},{"key":"1Key9","time":68036},{"key":"1Key5","time":68286},{"key":"1Key7","time":68286},{"key":"1Key5","time":68536},{"key":"1Key7","time":68536},{"key":"1Key9","time":68536},{"key":"1Key5","time":68661},{"key":"1Key2","time":68786},{"key":"1Key5","time":68786},{"key":"1Key4","time":69036},{"key":"1Key5","time":69036},{"key":"1Key7","time":69036},{"key":"1Key9","time":69036},{"key":"1Key7","time":69161},{"key":"1Key5","time":69286},{"key":"1Key9","time":69286},{"key":"1Key7","time":69536},{"key":"1Key9","time":69536},{"key":"1Key2","time":69786},{"key":"1Key8","time":69786},{"key":"1Key4","time":70036},{"key":"1Key7","time":70036},{"key":"1Key9","time":70036},{"key":"1Key2","time":70286},{"key":"1Key6","time":70286},{"key":"1Key4","time":70536},{"key":"1Key7","time":70536},{"key":"1Key9","time":70536},{"key":"1Key4","time":70661},{"key":"1Key2","time":70786},{"key":"1Key4","time":70786},{"key":"1Key4","time":71036},{"key":"1Key7","time":71036},{"key":"1Key9","time":71036},{"key":"1Key6","time":71161},{"key":"1Key2","time":71286},{"key":"1Key8","time":71286},{"key":"1Key8","time":71411},{"key":"1Key6","time":71536},{"key":"1Key8","time":71536},{"key":"1Key9","time":71536},{"key":"1Key8","time":71661},{"key":"1Key4","time":71786},{"key":"1Key7","time":71786},{"key":"1Key7","time":71911},{"key":"1Key2","time":72036},{"key":"1Key6","time":72036},{"key":"1Key9","time":72036},{"key":"1Key6","time":72161},{"key":"1Key5","time":72286},{"key":"1Key7","time":72286},{"key":"1Key5","time":72536},{"key":"1Key7","time":72536},{"key":"1Key9","time":72536},{"key":"1Key5","time":72661},{"key":"1Key2","time":72786},{"key":"1Key5","time":72786},{"key":"1Key4","time":73036},{"key":"1Key7","time":73036},{"key":"1Key9","time":73036},{"key":"1Key5","time":73161},{"key":"1Key5","time":73286},{"key":"1Key9","time":73286},{"key":"1Key7","time":73536},{"key":"1Key9","time":73536},{"key":"1Key2","time":73786},{"key":"1Key8","time":73786},{"key":"1Key4","time":74036},{"key":"1Key7","time":74036},{"key":"1Key9","time":74036},{"key":"1Key2","time":74286},{"key":"1Key6","time":74286},{"key":"1Key4","time":74536},{"key":"1Key7","time":74536},{"key":"1Key9","time":74536},{"key":"1Key4","time":74661},{"key":"1Key2","time":74786},{"key":"1Key4","time":74786},{"key":"1Key4","time":75036},{"key":"1Key7","time":75036},{"key":"1Key9","time":75036},{"key":"1Key6","time":75161},{"key":"1Key2","time":75286},{"key":"1Key8","time":75286},{"key":"1Key8","time":75411},{"key":"1Key6","time":75536},{"key":"1Key8","time":75536},{"key":"1Key9","time":75536},{"key":"1Key8","time":75661},{"key":"1Key4","time":75786},{"key":"1Key7","time":75786},{"key":"1Key2","time":76036},{"key":"1Key6","time":76036},{"key":"1Key9","time":76036},{"key":"1Key5","time":76286},{"key":"1Key7","time":76286},{"key":"1Key9","time":76286},{"key":"1Key5","time":76848},{"key":"1Key2","time":76973},{"key":"1Key5","time":76973},{"key":"1Key5","time":77223},{"key":"1Key7","time":77223},{"key":"1Key9","time":77223},{"key":"1Key2","time":77473},{"key":"1Key5","time":77473},{"key":"1Key4","time":77723},{"key":"1Key7","time":77723},{"key":"1Key9","time":77723},{"key":"1Key6","time":77848},{"key":"1Key5","time":77973},{"key":"1Key7","time":77973},{"key":"1Key7","time":78098},{"key":"1Key5","time":78223},{"key":"1Key7","time":78223},{"key":"1Key9","time":78223},{"key":"1Key5","time":78348},{"key":"1Key2","time":78473},{"key":"1Key5","time":78473},{"key":"1Key4","time":78723},{"key":"1Key5","time":78723},{"key":"1Key7","time":78723},{"key":"1Key9","time":78723},{"key":"1Key7","time":78848},{"key":"1Key2","time":78973},{"key":"1Key6","time":78973},{"key":"1Key4","time":79223},{"key":"1Key6","time":79223},{"key":"1Key9","time":79223},{"key":"1Key4","time":79473},{"key":"1Key2","time":79723},{"key":"1Key4","time":79723},{"key":"1Key6","time":79723},{"key":"1Key9","time":79723},{"key":"1Key5","time":79973},{"key":"1Key6","time":79973},{"key":"1Key5","time":80223},{"key":"1Key7","time":80223},{"key":"1Key9","time":80223},{"key":"1Key2","time":80473},{"key":"1Key5","time":80473},{"key":"1Key4","time":80723},{"key":"1Key5","time":80723},{"key":"1Key7","time":80723},{"key":"1Key9","time":80723},{"key":"1Key5","time":80848},{"key":"1Key2","time":80973},{"key":"1Key5","time":80973},{"key":"1Key5","time":81223},{"key":"1Key7","time":81223},{"key":"1Key9","time":81223},{"key":"1Key2","time":81473},{"key":"1Key5","time":81473},{"key":"1Key4","time":81723},{"key":"1Key7","time":81723},{"key":"1Key9","time":81723},{"key":"1Key6","time":81848},{"key":"1Key5","time":81973},{"key":"1Key7","time":81973},{"key":"1Key5","time":82223},{"key":"1Key7","time":82223},{"key":"1Key9","time":82223},{"key":"1Key5","time":82348},{"key":"1Key2","time":82473},{"key":"1Key5","time":82598},{"key":"1Key4","time":82723},{"key":"1Key5","time":82723},{"key":"1Key7","time":82723},{"key":"1Key9","time":82723},{"key":"1Key7","time":82848},{"key":"1Key2","time":82973},{"key":"1Key9","time":82973},{"key":"1Key9","time":83098},{"key":"1Key6","time":83223},{"key":"1Key9","time":83223},{"key":"1Key8","time":83348},{"key":"1Key4","time":83473},{"key":"1Key7","time":83473},{"key":"1Key7","time":83598},{"key":"1Key2","time":83723},{"key":"1Key6","time":83723},{"key":"1Key9","time":83723},{"key":"1Key5","time":83973},{"key":"1Key7","time":83973},{"key":"1Key5","time":84223},{"key":"1Key7","time":84223},{"key":"1Key9","time":84223},{"key":"1Key2","time":84473},{"key":"1Key5","time":84473},{"key":"1Key4","time":84723},{"key":"1Key5","time":84723},{"key":"1Key7","time":84723},{"key":"1Key9","time":84723},{"key":"1Key5","time":84848},{"key":"1Key5","time":84973},{"key":"1Key9","time":84973},{"key":"1Key7","time":85223},{"key":"1Key9","time":85223},{"key":"1Key2","time":85473},{"key":"1Key8","time":85473},{"key":"1Key4","time":85723},{"key":"1Key7","time":85723},{"key":"1Key9","time":85723},{"key":"1Key2","time":85973},{"key":"1Key6","time":85973},{"key":"1Key4","time":86223},{"key":"1Key7","time":86223},{"key":"1Key9","time":86223},{"key":"1Key4","time":86348},{"key":"1Key2","time":86473},{"key":"1Key4","time":86598},{"key":"1Key4","time":86723},{"key":"1Key7","time":86723},{"key":"1Key9","time":86723},{"key":"1Key6","time":86848},{"key":"1Key5","time":86973},{"key":"1Key9","time":86973},{"key":"1Key7","time":87223},{"key":"1Key9","time":87223},{"key":"1Key2","time":87473},{"key":"1Key8","time":87473},{"key":"1Key4","time":87723},{"key":"1Key7","time":87723},{"key":"1Key9","time":87723},{"key":"1Key2","time":87973},{"key":"1Key6","time":87973},{"key":"1Key4","time":88223},{"key":"1Key7","time":88223},{"key":"1Key9","time":88223},{"key":"1Key4","time":88348},{"key":"1Key2","time":88473},{"key":"1Key4","time":88598},{"key":"1Key4","time":88723},{"key":"1Key7","time":88723},{"key":"1Key9","time":88723},{"key":"1Key6","time":88848},{"key":"1Key5","time":88973},{"key":"1Key9","time":88973},{"key":"1Key7","time":89223},{"key":"1Key9","time":89223},{"key":"1Key2","time":89473},{"key":"1Key8","time":89473},{"key":"1Key4","time":89723},{"key":"1Key7","time":89723},{"key":"1Key9","time":89723},{"key":"1Key5","time":89973},{"key":"1Key9","time":89973},{"key":"1Key7","time":90223},{"key":"1Key9","time":90223},{"key":"1Key2","time":90473},{"key":"1Key8","time":90473},{"key":"1Key4","time":90723},{"key":"1Key7","time":90723},{"key":"1Key9","time":90723},{"key":"1Key5","time":90973},{"key":"1Key9","time":90973},{"key":"1Key7","time":91223},{"key":"1Key9","time":91223},{"key":"1Key5","time":91473},{"key":"1Key9","time":91473},{"key":"1Key7","time":91723},{"key":"1Key9","time":91723},{"key":"1Key5","time":91973},{"key":"1Key9","time":91973},{"key":"1Key5","time":92223},{"key":"1Key9","time":92223},{"key":"1Key5","time":92473},{"key":"1Key9","time":92473},{"key":"1Key5","time":92598},{"key":"1Key9","time":92598},{"key":"1Key5","time":92723},{"key":"1Key9","time":92723},{"key":"1Key5","time":92848},{"key":"1Key2","time":92973},{"key":"1Key5","time":92973},{"key":"1Key5","time":93223},{"key":"1Key7","time":93223},{"key":"1Key9","time":93223},{"key":"1Key2","time":93473},{"key":"1Key5","time":93473},{"key":"1Key4","time":93723},{"key":"1Key7","time":93723},{"key":"1Key9","time":93723},{"key":"1Key6","time":93848},{"key":"1Key5","time":93973},{"key":"1Key7","time":93973},{"key":"1Key7","time":94098},{"key":"1Key5","time":94223},{"key":"1Key7","time":94223},{"key":"1Key9","time":94223},{"key":"1Key5","time":94348},{"key":"1Key2","time":94473},{"key":"1Key5","time":94473},{"key":"1Key4","time":94723},{"key":"1Key5","time":94723},{"key":"1Key7","time":94723},{"key":"1Key9","time":94723},{"key":"1Key7","time":94848},{"key":"1Key2","time":94973},{"key":"1Key6","time":94973},{"key":"1Key4","time":95223},{"key":"1Key6","time":95223},{"key":"1Key9","time":95223},{"key":"1Key4","time":95473},{"key":"1Key2","time":95723},{"key":"1Key4","time":95723},{"key":"1Key6","time":95723},{"key":"1Key9","time":95723},{"key":"1Key5","time":95973},{"key":"1Key6","time":95973},{"key":"1Key5","time":96223},{"key":"1Key7","time":96223},{"key":"1Key9","time":96223},{"key":"1Key2","time":96473},{"key":"1Key5","time":96473},{"key":"1Key4","time":96723},{"key":"1Key5","time":96723},{"key":"1Key7","time":96723},{"key":"1Key9","time":96723},{"key":"1Key5","time":96848},{"key":"1Key2","time":96973},{"key":"1Key5","time":96973},{"key":"1Key5","time":97223},{"key":"1Key7","time":97223},{"key":"1Key9","time":97223},{"key":"1Key2","time":97473},{"key":"1Key5","time":97473},{"key":"1Key4","time":97723},{"key":"1Key7","time":97723},{"key":"1Key9","time":97723},{"key":"1Key6","time":97848},{"key":"1Key5","time":97973},{"key":"1Key7","time":97973},{"key":"1Key5","time":98223},{"key":"1Key7","time":98223},{"key":"1Key9","time":98223},{"key":"1Key5","time":98348},{"key":"1Key2","time":98473},{"key":"1Key5","time":98598},{"key":"1Key4","time":98723},{"key":"1Key5","time":98723},{"key":"1Key7","time":98723},{"key":"1Key9","time":98723},{"key":"1Key7","time":98848},{"key":"1Key2","time":98973},{"key":"1Key9","time":98973},{"key":"1Key9","time":99098},{"key":"1Key6","time":99223},{"key":"1Key9","time":99223},{"key":"1Key8","time":99348},{"key":"1Key4","time":99473},{"key":"1Key7","time":99473},{"key":"1Key7","time":99598},{"key":"1Key2","time":99723},{"key":"1Key6","time":99723},{"key":"1Key9","time":99723},{"key":"1Key5","time":99973},{"key":"1Key7","time":99973},{"key":"1Key5","time":100223},{"key":"1Key7","time":100223},{"key":"1Key9","time":100223},{"key":"1Key2","time":100473},{"key":"1Key5","time":100473},{"key":"1Key4","time":100723},{"key":"1Key5","time":100723},{"key":"1Key7","time":100723},{"key":"1Key9","time":100723},{"key":"1Key5","time":100848},{"key":"1Key5","time":100973},{"key":"1Key9","time":100973},{"key":"1Key7","time":101223},{"key":"1Key9","time":101223},{"key":"1Key2","time":101473},{"key":"1Key8","time":101473},{"key":"1Key4","time":101723},{"key":"1Key7","time":101723},{"key":"1Key9","time":101723},{"key":"1Key2","time":101973},{"key":"1Key6","time":101973},{"key":"1Key4","time":102223},{"key":"1Key7","time":102223},{"key":"1Key9","time":102223},{"key":"1Key4","time":102348},{"key":"1Key2","time":102473},{"key":"1Key4","time":102598},{"key":"1Key4","time":102723},{"key":"1Key7","time":102723},{"key":"1Key9","time":102723},{"key":"1Key6","time":102848},{"key":"1Key2","time":102973},{"key":"1Key8","time":102973},{"key":"1Key8","time":103098},{"key":"1Key6","time":103223},{"key":"1Key8","time":103223},{"key":"1Key9","time":103223},{"key":"1Key8","time":103348},{"key":"1Key4","time":103473},{"key":"1Key7","time":103473},{"key":"1Key7","time":103598},{"key":"1Key2","time":103723},{"key":"1Key6","time":103723},{"key":"1Key9","time":103723},{"key":"1Key6","time":103848},{"key":"1Key5","time":103973},{"key":"1Key7","time":103973},{"key":"1Key5","time":104223},{"key":"1Key7","time":104223},{"key":"1Key9","time":104223},{"key":"1Key5","time":104348},{"key":"1Key2","time":104473},{"key":"1Key4","time":104723},{"key":"1Key7","time":104723},{"key":"1Key9","time":104723},{"key":"1Key5","time":104848},{"key":"1Key5","time":104973},{"key":"1Key9","time":104973},{"key":"1Key7","time":105223},{"key":"1Key9","time":105223},{"key":"1Key2","time":105473},{"key":"1Key8","time":105473},{"key":"1Key4","time":105723},{"key":"1Key7","time":105723},{"key":"1Key9","time":105723},{"key":"1Key2","time":105973},{"key":"1Key6","time":105973},{"key":"1Key4","time":106223},{"key":"1Key7","time":106223},{"key":"1Key9","time":106223},{"key":"1Key2","time":106473},{"key":"1Key4","time":106473},{"key":"1Key4","time":106723},{"key":"1Key7","time":106723},{"key":"1Key9","time":106723},{"key":"1Key6","time":106848},{"key":"1Key2","time":106973},{"key":"1Key8","time":106973},{"key":"1Key8","time":107098},{"key":"1Key6","time":107223},{"key":"1Key8","time":107223},{"key":"1Key9","time":107223},{"key":"1Key8","time":107348},{"key":"1Key4","time":107473},{"key":"1Key7","time":107473},{"key":"1Key2","time":107723},{"key":"1Key6","time":107723},{"key":"1Key9","time":107723},{"key":"1Key5","time":107973},{"key":"1Key7","time":107973},{"key":"1Key9","time":107973},{"key":"1Key5","time":108223},{"key":"1Key5","time":108348},{"key":"1Key5","time":108723},{"key":"1Key2","time":108848},{"key":"1Key5","time":108848},{"key":"1Key5","time":109098},{"key":"1Key7","time":109098},{"key":"1Key9","time":109098},{"key":"1Key2","time":109348},{"key":"1Key5","time":109348},{"key":"1Key4","time":109598},{"key":"1Key7","time":109598},{"key":"1Key9","time":109598},{"key":"1Key6","time":109723},{"key":"1Key5","time":109848},{"key":"1Key7","time":109848},{"key":"1Key7","time":109973},{"key":"1Key5","time":110098},{"key":"1Key7","time":110098},{"key":"1Key9","time":110098},{"key":"1Key5","time":110223},{"key":"1Key2","time":110348},{"key":"1Key5","time":110348},{"key":"1Key4","time":110598},{"key":"1Key5","time":110598},{"key":"1Key7","time":110598},{"key":"1Key9","time":110598},{"key":"1Key7","time":110723},{"key":"1Key2","time":110848},{"key":"1Key6","time":110848},{"key":"1Key4","time":111098},{"key":"1Key6","time":111098},{"key":"1Key9","time":111098},{"key":"1Key4","time":111348},{"key":"1Key2","time":111598},{"key":"1Key4","time":111598},{"key":"1Key6","time":111598},{"key":"1Key9","time":111598},{"key":"1Key5","time":111848},{"key":"1Key6","time":111848},{"key":"1Key5","time":112098},{"key":"1Key7","time":112098},{"key":"1Key9","time":112098},{"key":"1Key2","time":112348},{"key":"1Key5","time":112348},{"key":"1Key4","time":112598},{"key":"1Key5","time":112598},{"key":"1Key7","time":112598},{"key":"1Key9","time":112598},{"key":"1Key5","time":112723},{"key":"1Key2","time":112848},{"key":"1Key5","time":112848},{"key":"1Key5","time":113098},{"key":"1Key7","time":113098},{"key":"1Key9","time":113098},{"key":"1Key2","time":113348},{"key":"1Key5","time":113348},{"key":"1Key4","time":113598},{"key":"1Key7","time":113598},{"key":"1Key9","time":113598},{"key":"1Key6","time":113723},{"key":"1Key5","time":113848},{"key":"1Key7","time":113848},{"key":"1Key5","time":114098},{"key":"1Key7","time":114098},{"key":"1Key9","time":114098},{"key":"1Key5","time":114223},{"key":"1Key2","time":114348},{"key":"1Key5","time":114473},{"key":"1Key4","time":114598},{"key":"1Key5","time":114598},{"key":"1Key7","time":114598},{"key":"1Key9","time":114598},{"key":"1Key7","time":114723},{"key":"1Key2","time":114848},{"key":"1Key9","time":114848},{"key":"1Key9","time":114973},{"key":"1Key6","time":115098},{"key":"1Key9","time":115098},{"key":"1Key8","time":115223},{"key":"1Key4","time":115348},{"key":"1Key7","time":115348},{"key":"1Key7","time":115473},{"key":"1Key2","time":115598},{"key":"1Key6","time":115598},{"key":"1Key9","time":115598},{"key":"1Key5","time":115848},{"key":"1Key7","time":115848},{"key":"1Key5","time":116098},{"key":"1Key7","time":116098},{"key":"1Key9","time":116098},{"key":"1Key2","time":116348},{"key":"1Key5","time":116348},{"key":"1Key4","time":116598},{"key":"1Key5","time":116598},{"key":"1Key7","time":116598},{"key":"1Key9","time":116598},{"key":"1Key5","time":116723},{"key":"1Key5","time":116848},{"key":"1Key9","time":116848},{"key":"1Key7","time":117098},{"key":"1Key9","time":117098},{"key":"1Key2","time":117348},{"key":"1Key8","time":117348},{"key":"1Key4","time":117598},{"key":"1Key7","time":117598},{"key":"1Key9","time":117598},{"key":"1Key2","time":117848},{"key":"1Key6","time":117848},{"key":"1Key4","time":118098},{"key":"1Key7","time":118098},{"key":"1Key9","time":118098},{"key":"1Key4","time":118223},{"key":"1Key2","time":118348},{"key":"1Key4","time":118473},{"key":"1Key4","time":118598},{"key":"1Key7","time":118598},{"key":"1Key9","time":118598},{"key":"1Key6","time":118723},{"key":"1Key2","time":118848},{"key":"1Key8","time":118848},{"key":"1Key8","time":118973},{"key":"1Key6","time":119098},{"key":"1Key8","time":119098},{"key":"1Key9","time":119098},{"key":"1Key8","time":119223},{"key":"1Key4","time":119348},{"key":"1Key7","time":119348},{"key":"1Key7","time":119473},{"key":"1Key2","time":119598},{"key":"1Key6","time":119598},{"key":"1Key9","time":119598},{"key":"1Key6","time":119723},{"key":"1Key5","time":119848},{"key":"1Key7","time":119848},{"key":"1Key5","time":120098},{"key":"1Key7","time":120098},{"key":"1Key9","time":120098},{"key":"1Key5","time":120223},{"key":"1Key2","time":120348},{"key":"1Key4","time":120598},{"key":"1Key7","time":120598},{"key":"1Key9","time":120598},{"key":"1Key5","time":120723},{"key":"1Key5","time":120848},{"key":"1Key9","time":120848},{"key":"1Key7","time":121098},{"key":"1Key9","time":121098},{"key":"1Key2","time":121348},{"key":"1Key8","time":121348},{"key":"1Key4","time":121598},{"key":"1Key7","time":121598},{"key":"1Key9","time":121598},{"key":"1Key2","time":121848},{"key":"1Key6","time":121848},{"key":"1Key4","time":122098},{"key":"1Key7","time":122098},{"key":"1Key9","time":122098},{"key":"1Key2","time":122348},{"key":"1Key4","time":122348},{"key":"1Key4","time":122598},{"key":"1Key7","time":122598},{"key":"1Key9","time":122598},{"key":"1Key6","time":122723},{"key":"1Key2","time":122848},{"key":"1Key8","time":122848},{"key":"1Key8","time":122973},{"key":"1Key6","time":123098},{"key":"1Key8","time":123098},{"key":"1Key9","time":123098},{"key":"1Key8","time":123223},{"key":"1Key4","time":123348},{"key":"1Key7","time":123348},{"key":"1Key2","time":123598},{"key":"1Key6","time":123598},{"key":"1Key9","time":123598},{"key":"1Key5","time":123848},{"key":"1Key7","time":123848},{"key":"1Key9","time":123848},{"key":"1Key5","time":124098},{"key":"1Key5","time":124223},{"key":"1Key5","time":124660},{"key":"1Key7","time":124910},{"key":"1Key9","time":124910},{"key":"1Key2","time":125160},{"key":"1Key4","time":125410},{"key":"1Key7","time":125410},{"key":"1Key9","time":125410},{"key":"1Key5","time":125660},{"key":"1Key7","time":125910},{"key":"1Key9","time":125910},{"key":"1Key2","time":126160},{"key":"1Key4","time":126410},{"key":"1Key7","time":126410},{"key":"1Key9","time":126410},{"key":"1Key2","time":126660},{"key":"1Key6","time":126910},{"key":"1Key9","time":126910},{"key":"1Key4","time":127160},{"key":"1Key2","time":127410},{"key":"1Key6","time":127410},{"key":"1Key9","time":127410},{"key":"1Key5","time":127660},{"key":"1Key7","time":127910},{"key":"1Key9","time":127910},{"key":"1Key2","time":128160},{"key":"1Key4","time":128410},{"key":"1Key7","time":128410},{"key":"1Key9","time":128410},{"key":"1Key5","time":128660},{"key":"1Key7","time":128910},{"key":"1Key9","time":128910},{"key":"1Key2","time":129160},{"key":"1Key4","time":129410},{"key":"1Key7","time":129410},{"key":"1Key9","time":129410},{"key":"1Key5","time":129660},{"key":"1Key7","time":129910},{"key":"1Key9","time":129910},{"key":"1Key2","time":130160},{"key":"1Key4","time":130410},{"key":"1Key7","time":130410},{"key":"1Key9","time":130410},{"key":"1Key2","time":130660},{"key":"1Key6","time":130910},{"key":"1Key9","time":130910},{"key":"1Key4","time":131160},{"key":"1Key2","time":131410},{"key":"1Key6","time":131410},{"key":"1Key9","time":131410},{"key":"1Key5","time":131660},{"key":"1Key7","time":131910},{"key":"1Key9","time":131910},{"key":"1Key2","time":132160},{"key":"1Key4","time":132410},{"key":"1Key7","time":132410},{"key":"1Key9","time":132410},{"key":"1Key5","time":132660},{"key":"1Key7","time":132910},{"key":"1Key9","time":132910},{"key":"1Key2","time":133160},{"key":"1Key4","time":133410},{"key":"1Key7","time":133410},{"key":"1Key9","time":133410},{"key":"1Key2","time":133660},{"key":"1Key7","time":133910},{"key":"1Key9","time":133910},{"key":"1Key2","time":134160},{"key":"1Key4","time":134410},{"key":"1Key7","time":134410},{"key":"1Key9","time":134410},{"key":"1Key2","time":134660},{"key":"1Key6","time":134910},{"key":"1Key9","time":134910},{"key":"1Key4","time":135160},{"key":"1Key2","time":135410},{"key":"1Key6","time":135410},{"key":"1Key9","time":135410},{"key":"1Key5","time":135660},{"key":"1Key7","time":135910},{"key":"1Key9","time":135910},{"key":"1Key2","time":136160},{"key":"1Key4","time":136410},{"key":"1Key7","time":136410},{"key":"1Key9","time":136410},{"key":"1Key5","time":136660},{"key":"1Key7","time":136910},{"key":"1Key9","time":136910},{"key":"1Key2","time":137160},{"key":"1Key4","time":137410},{"key":"1Key7","time":137410},{"key":"1Key9","time":137410},{"key":"1Key2","time":137660},{"key":"1Key7","time":137910},{"key":"1Key9","time":137910},{"key":"1Key2","time":138160},{"key":"1Key4","time":138410},{"key":"1Key7","time":138410},{"key":"1Key9","time":138410},{"key":"1Key2","time":138660},{"key":"1Key6","time":138910},{"key":"1Key9","time":138910},{"key":"1Key4","time":139160},{"key":"1Key2","time":139410},{"key":"1Key6","time":139410},{"key":"1Key9","time":139410},{"key":"1Key5","time":139660},{"key":"1Key7","time":139660},{"key":"1Key9","time":139660}]}]